{
	"__v" : NumberInt("0"),
	"_id" : ObjectId("5a6a0268793ed70468152251"),
	"addedDate" : ISODate("2018-01-25T18:14:32.635+02:00"),
	"prediction" : "",
	"resurse" : "over25tips",
	"team1" : "Independiente ",
	"team2" : "Rosario Central"
},
{
	"__v" : NumberInt("0"),
	"_id" : ObjectId("5a6a0268793ed70468152253"),
	"addedDate" : ISODate("2018-01-25T18:14:32.645+02:00"),
	"prediction" : "",
	"resurse" : "over25tips",
	"team1" : "CD Marathon ",
	"team2" : "Lobos UPNFM"
},
{
	"__v" : NumberInt("0"),
	"_id" : ObjectId("5a6a0268793ed70468152252"),
	"addedDate" : ISODate("2018-01-25T18:14:32.642+02:00"),
	"prediction" : "Under 2.5 goals ",
	"resurse" : "over25tips",
	"team1" : "CA Talleres Remedios de Escalada ",
	"team2" : "Barracas Central"
},
{
	"__v" : NumberInt("0"),
	"_id" : ObjectId("5a6a0268793ed70468152255"),
	"addedDate" : ISODate("2018-01-25T18:14:32.648+02:00"),
	"prediction" : "Over 2.5 goals ",
	"resurse" : "over25tips",
	"team1" : "Honduras Progreso ",
	"team2" : "Real Espana"
},
{
	"__v" : NumberInt("0"),
	"_id" : ObjectId("5a6a0268793ed70468152256"),
	"addedDate" : ISODate("2018-01-25T18:14:32.650+02:00"),
	"prediction" : "Over 2.5 goals and Btts ",
	"resurse" : "over25tips",
	"team1" : "Juticalpa ",
	"team2" : "CD Olimpia"
},
{
	"__v" : NumberInt("0"),
	"_id" : ObjectId("5a6a0268793ed70468152254"),
	"addedDate" : ISODate("2018-01-25T18:14:32.647+02:00"),
	"prediction" : "Over 2.5 goals ",
	"resurse" : "over25tips",
	"team1" : "CD Motagua ",
	"team2" : "CD Real Sociedad"
},
{
	"__v" : NumberInt("0"),
	"_id" : ObjectId("5a6a0268793ed70468152257"),
	"addedDate" : ISODate("2018-01-25T18:14:32.652+02:00"),
	"prediction" : "Over 2.5 goals and Btts ",
	"resurse" : "over25tips",
	"team1" : "CD Vida ",
	"team2" : "Platense FC"
},
{
	"__v" : NumberInt("0"),
	"_id" : ObjectId("5a6a0268793ed70468152258"),
	"addedDate" : ISODate("2018-01-25T18:14:32.655+02:00"),
	"prediction" : "Under 2.5 goals ",
	"resurse" : "over25tips",
	"team1" : "Mirassol ",
	"team2" : "Sao Paulo"
},
{
	"__v" : NumberInt("0"),
	"_id" : ObjectId("5a6a0268793ed70468152259"),
	"addedDate" : ISODate("2018-01-25T18:14:32.657+02:00"),
	"prediction" : "Over 2.5 goals ",
	"resurse" : "over25tips",
	"team1" : "Alianza FC ",
	"team2" : "CD Sonsonate"
},
{
	"__v" : NumberInt("0"),
	"_id" : ObjectId("5a6a0268793ed7046815225b"),
	"addedDate" : ISODate("2018-01-25T18:14:32.663+02:00"),
	"prediction" : "",
	"resurse" : "over25tips",
	"team1" : "CD Dragon ",
	"team2" : "CD Aguila"
},
{
	"__v" : NumberInt("0"),
	"_id" : ObjectId("5a6a0268793ed7046815225a"),
	"addedDate" : ISODate("2018-01-25T18:14:32.662+02:00"),
	"prediction" : "Under 2.5 goals ",
	"resurse" : "over25tips",
	"team1" : "CD Chalatenango ",
	"team2" : "CD FAS"
},
{
	"__v" : NumberInt("0"),
	"_id" : ObjectId("5a6a0268793ed7046815225c"),
	"addedDate" : ISODate("2018-01-25T18:14:32.665+02:00"),
	"prediction" : "",
	"resurse" : "over25tips",
	"team1" : "Firpo ",
	"team2" : "Pasaquina"
},
{
	"__v" : NumberInt("0"),
	"_id" : ObjectId("5a6a0268793ed7046815225d"),
	"addedDate" : ISODate("2018-01-25T18:14:32.667+02:00"),
	"prediction" : "",
	"resurse" : "over25tips",
	"team1" : "Enyimba ",
	"team2" : "Nasarawa United"
},
{
	"__v" : NumberInt("0"),
	"_id" : ObjectId("5a6a0268793ed7046815225f"),
	"addedDate" : ISODate("2018-01-25T18:14:32.671+02:00"),
	"prediction" : "Over 2.5 goals ",
	"resurse" : "over25tips",
	"team1" : "Dynamo Dresden ",
	"team2" : "St. Pauli"
},
{
	"__v" : NumberInt("0"),
	"_id" : ObjectId("5a6a0268793ed70468152260"),
	"addedDate" : ISODate("2018-01-25T18:14:32.673+02:00"),
	"prediction" : "Away Win ",
	"resurse" : "over25tips",
	"team1" : "Strasbourg ",
	"team2" : "Lille"
},
{
	"__v" : NumberInt("0"),
	"_id" : ObjectId("5a6a0268793ed70468152262"),
	"addedDate" : ISODate("2018-01-25T18:14:32.675+02:00"),
	"prediction" : "Home Win ",
	"resurse" : "over25tips",
	"team1" : "FC Ufa ",
	"team2" : "Wisla Plock"
},
{
	"__v" : NumberInt("0"),
	"_id" : ObjectId("5a6a0268793ed70468152263"),
	"addedDate" : ISODate("2018-01-25T18:14:32.676+02:00"),
	"prediction" : "",
	"resurse" : "over25tips",
	"team1" : "FK Akhmat ",
	"team2" : "Alanyaspor"
},
{
	"__v" : NumberInt("0"),
	"_id" : ObjectId("5a6a0268793ed70468152265"),
	"addedDate" : ISODate("2018-01-25T18:14:32.679+02:00"),
	"prediction" : "Over 2.5 goals ",
	"resurse" : "over25tips",
	"team1" : "PFC CSKA-Sofia ",
	"team2" : "AaB"
},
{
	"__v" : NumberInt("0"),
	"_id" : ObjectId("5a6a0268793ed70468152264"),
	"addedDate" : ISODate("2018-01-25T18:14:32.677+02:00"),
	"prediction" : "Home Win ",
	"resurse" : "over25tips",
	"team1" : "OB ",
	"team2" : "Vejle Boldklub"
},
{
	"__v" : NumberInt("0"),
	"_id" : ObjectId("5a6a0268793ed70468152267"),
	"addedDate" : ISODate("2018-01-25T18:14:32.697+02:00"),
	"prediction" : "Under 2.5 goals ",
	"resurse" : "over25tips",
	"team1" : "IK Frej Taeby ",
	"team2" : "Dalkurd FF"
},
{
	"__v" : NumberInt("0"),
	"_id" : ObjectId("5a6a0268793ed70468152268"),
	"addedDate" : ISODate("2018-01-25T18:14:32.698+02:00"),
	"prediction" : "",
	"resurse" : "over25tips",
	"team1" : "Odds Ballklubb ",
	"team2" : "Shanghai Shenxin"
},
{
	"__v" : NumberInt("0"),
	"_id" : ObjectId("5a6a0268793ed70468152269"),
	"addedDate" : ISODate("2018-01-25T18:14:32.699+02:00"),
	"prediction" : "Over 2.5 goals ",
	"resurse" : "over25tips",
	"team1" : "Zenit St. Petersburg ",
	"team2" : "Slavia Prague"
},
{
	"__v" : NumberInt("0"),
	"_id" : ObjectId("5a6a0268793ed7046815226a"),
	"addedDate" : ISODate("2018-01-25T18:14:32.700+02:00"),
	"prediction" : "Over 2.5 goals ",
	"resurse" : "over25tips",
	"team1" : "Mjoendalen ",
	"team2" : "Sandefjord"
},
{
	"__v" : NumberInt("0"),
	"_id" : ObjectId("5a6a0268793ed7046815226c"),
	"addedDate" : ISODate("2018-01-25T18:14:32.712+02:00"),
	"prediction" : "Over 2.5 goals ",
	"resurse" : "over25tips",
	"team1" : "Beitar Jerusalem ",
	"team2" : "Hapoel Marmorek"
},
{
	"__v" : NumberInt("0"),
	"_id" : ObjectId("5a6a0268793ed7046815226e"),
	"addedDate" : ISODate("2018-01-25T18:14:32.715+02:00"),
	"prediction" : "Over 2.5 goals ",
	"resurse" : "over25tips",
	"team1" : "Ituano FC ",
	"team2" : "Santo Andre"
},
{
	"__v" : NumberInt("0"),
	"_id" : ObjectId("5a6a0268793ed7046815226d"),
	"addedDate" : ISODate("2018-01-25T18:14:32.713+02:00"),
	"prediction" : "Under 2.5 goals ",
	"resurse" : "over25tips",
	"team1" : "Bragantino ",
	"team2" : "Sao Bento"
},
{
	"__v" : NumberInt("0"),
	"_id" : ObjectId("5a6a0268793ed7046815226f"),
	"addedDate" : ISODate("2018-01-25T18:14:32.715+02:00"),
	"prediction" : "Over 2.5 goals ",
	"resurse" : "over25tips",
	"team1" : "Ponte Preta ",
	"team2" : "Santos FC"
},
{
	"__v" : NumberInt("0"),
	"_id" : ObjectId("5a6a0268793ed7046815225e"),
	"addedDate" : ISODate("2018-01-25T18:14:32.670+02:00"),
	"prediction" : "Home Win ",
	"resurse" : "over25tips",
	"team1" : "Barcelona ",
	"team2" : "Espanyol"
},
{
	"__v" : NumberInt("0"),
	"_id" : ObjectId("5a6a0268793ed70468152271"),
	"addedDate" : ISODate("2018-01-25T18:14:32.717+02:00"),
	"prediction" : "",
	"resurse" : "over25tips",
	"team1" : "Monterrey ",
	"team2" : "Correcaminos de la UAT"
},
{
	"__v" : NumberInt("0"),
	"_id" : ObjectId("5a6a0268793ed70468152261"),
	"addedDate" : ISODate("2018-01-25T18:14:32.674+02:00"),
	"prediction" : "Over 2.5 goals ",
	"resurse" : "over25tips",
	"team1" : "Club Brugge ",
	"team2" : "Oostende"
},
{
	"__v" : NumberInt("0"),
	"_id" : ObjectId("5a6a0268793ed70468152272"),
	"addedDate" : ISODate("2018-01-25T18:14:32.719+02:00"),
	"prediction" : "",
	"resurse" : "over25tips",
	"team1" : "Santos ",
	"team2" : "Toluca"
},
{
	"__v" : NumberInt("0"),
	"_id" : ObjectId("5a6a0268793ed70468152266"),
	"addedDate" : ISODate("2018-01-25T18:14:32.696+02:00"),
	"prediction" : "Over 2.5 goals and Btts ",
	"resurse" : "over25tips",
	"team1" : "FC Koebenhavn ",
	"team2" : "Guangzhou Evergrande"
},
{
	"__v" : NumberInt("0"),
	"_id" : ObjectId("5a6a0268793ed7046815226b"),
	"addedDate" : ISODate("2018-01-25T18:14:32.710+02:00"),
	"prediction" : "Away Win ",
	"resurse" : "over25tips",
	"team1" : "PAS Giannina ",
	"team2" : "AE Larissa"
},
{
	"__v" : NumberInt("0"),
	"_id" : ObjectId("5a6a0268793ed70468152270"),
	"addedDate" : ISODate("2018-01-25T18:14:32.716+02:00"),
	"prediction" : "Home Win ",
	"resurse" : "over25tips",
	"team1" : "Palmeiras ",
	"team2" : "Red Bull Brasil"
},
{
	"__v" : NumberInt("0"),
	"_id" : ObjectId("5a6a0268793ed70468152273"),
	"addedDate" : ISODate("2018-01-25T18:14:32.720+02:00"),
	"prediction" : "Over 2.5 goals ",
	"resurse" : "over25tips",
	"team1" : "Pumas ",
	"team2" : "FC Juarez"
},
{
	"__v" : NumberInt("0"),
	"_id" : ObjectId("5a6a0268793ed70468152274"),
	"addedDate" : ISODate("2018-01-25T18:14:32.720+02:00"),
	"prediction" : "Under 2.5 goals ",
	"resurse" : "over25tips",
	"team1" : "Jaibos Tampico Madero ",
	"team2" : "Atlas"
},
{
	"__v" : NumberInt("0"),
	"_id" : ObjectId("5a6a0268793ed70468152275"),
	"addedDate" : ISODate("2018-01-25T18:14:32.721+02:00"),
	"prediction" : "Over 2.5 goals ",
	"resurse" : "over25tips",
	"team1" : "Deportivo Saprissa ",
	"team2" : "Grecia"
},
{
	"__v" : NumberInt("0"),
	"_id" : ObjectId("5a6a0268793ed70468152276"),
	"addedDate" : ISODate("2018-01-25T18:14:32.722+02:00"),
	"prediction" : "Home Win ",
	"resurse" : "over25tips",
	"team1" : "LD Alajuelense ",
	"team2" : "AD Municipal Liberia"
},
{
	"__v" : NumberInt("0"),
	"_id" : ObjectId("5a6a0268793ed70468152277"),
	"addedDate" : ISODate("2018-01-25T18:14:32.722+02:00"),
	"prediction" : "",
	"resurse" : "over25tips",
	"team1" : "Municipal Perez Zeledon ",
	"team2" : "C.S. Cartagines"
},
{
	"__v" : NumberInt("0"),
	"_id" : ObjectId("5a6a0268793ed70468152279"),
	"addedDate" : ISODate("2018-01-25T18:14:32.724+02:00"),
	"prediction" : "Over 2.5 goals ",
	"resurse" : "over25tips",
	"team1" : "Atletico de Kolkata ",
	"team2" : "Chennaiyin FC"
},
{
	"__v" : NumberInt("0"),
	"_id" : ObjectId("5a6a0268793ed70468152278"),
	"addedDate" : ISODate("2018-01-25T18:14:32.723+02:00"),
	"prediction" : "Under 2.5 goals ",
	"resurse" : "over25tips",
	"team1" : "Santos de Guapiles ",
	"team2" : "Universidad de Costa Rica"
},
{
	"__v" : NumberInt("0"),
	"_id" : ObjectId("5a6a0268793ed7046815227a"),
	"addedDate" : ISODate("2018-01-25T18:14:32.725+02:00"),
	"prediction" : "",
	"resurse" : "over25tips",
	"team1" : "Aizawl ",
	"team2" : "Mohun Bagan"
},
{
	"__v" : NumberInt("0"),
	"_id" : ObjectId("5a6a0268793ed7046815227b"),
	"addedDate" : ISODate("2018-01-25T18:14:32.725+02:00"),
	"prediction" : "",
	"resurse" : "over25tips",
	"team1" : "Esteghlal ",
	"team2" : "Pars Jonoubi Jam Bushehr"
},
{
	"__v" : NumberInt("0"),
	"_id" : ObjectId("5a6a0268793ed7046815227c"),
	"addedDate" : ISODate("2018-01-25T18:14:32.726+02:00"),
	"prediction" : "",
	"resurse" : "over25tips",
	"team1" : "Gostaresh Foolad FC ",
	"team2" : "Naft Tehran"
},
{
	"__v" : NumberInt("0"),
	"_id" : ObjectId("5a6a0268793ed7046815227d"),
	"addedDate" : ISODate("2018-01-25T18:14:32.727+02:00"),
	"prediction" : "",
	"resurse" : "over25tips",
	"team1" : "Saipa ",
	"team2" : "Padideh FC"
},
{
	"__v" : NumberInt("0"),
	"_id" : ObjectId("5a6a0268793ed7046815227e"),
	"addedDate" : ISODate("2018-01-25T18:14:32.727+02:00"),
	"prediction" : "Under 2.5 goals ",
	"resurse" : "over25tips",
	"team1" : "Sanat Naft Abadan ",
	"team2" : "Sepidrood Rasht"
},
{
	"__v" : NumberInt("0"),
	"_id" : ObjectId("5a6a0268793ed7046815227f"),
	"addedDate" : ISODate("2018-01-25T18:14:32.728+02:00"),
	"prediction" : "Over 2.5 goals ",
	"resurse" : "over25tips",
	"team1" : "Melbourne City FC ",
	"team2" : "Newcastle Jets"
},
{
	"__v" : NumberInt("0"),
	"_id" : ObjectId("5a6a0268793ed70468152280"),
	"addedDate" : ISODate("2018-01-25T18:14:32.730+02:00"),
	"prediction" : "Under 2.5 goals ",
	"resurse" : "over25tips",
	"team1" : "US Biskra ",
	"team2" : "ES Setif"
},
{
	"__v" : NumberInt("0"),
	"_id" : ObjectId("5a6a0268793ed70468152281"),
	"addedDate" : ISODate("2018-01-25T18:14:32.732+02:00"),
	"prediction" : "",
	"resurse" : "over25tips",
	"team1" : "El Raja Marsa Matruh ",
	"team2" : "Al Ahly"
},
{
	"__v" : NumberInt("0"),
	"_id" : ObjectId("5a6a0268793ed70468152282"),
	"addedDate" : ISODate("2018-01-25T18:14:32.733+02:00"),
	"prediction" : "Under 2.5 goals ",
	"resurse" : "over25tips",
	"team1" : "Misr El-Maqasa ",
	"team2" : "El Entag El Harby"
},
{
	"__v" : NumberInt("0"),
	"_id" : ObjectId("5a6a0268793ed70468152283"),
	"addedDate" : ISODate("2018-01-25T18:14:32.735+02:00"),
	"prediction" : "Over 2.5 goals ",
	"resurse" : "over25tips",
	"team1" : "Astra Giurgiu ",
	"team2" : "Ural"
},
{
	"__v" : NumberInt("0"),
	"_id" : ObjectId("5a6a0268793ed70468152284"),
	"addedDate" : ISODate("2018-01-25T18:14:32.736+02:00"),
	"prediction" : "",
	"resurse" : "over25tips",
	"team1" : "FK Akhmat ",
	"team2" : "FC Kyzylzhar Petropavlovsk"
},
{
	"__v" : NumberInt("0"),
	"_id" : ObjectId("5a6a0268793ed70468152285"),
	"addedDate" : ISODate("2018-01-25T18:14:32.737+02:00"),
	"prediction" : "Over 2.5 goals ",
	"resurse" : "over25tips",
	"team1" : "Pau ",
	"team2" : "Creteil"
},
{
	"__v" : NumberInt("0"),
	"_id" : ObjectId("5a6a0268793ed70468152286"),
	"addedDate" : ISODate("2018-01-25T18:14:32.738+02:00"),
	"prediction" : "Under 2.5 goals ",
	"resurse" : "over25tips",
	"team1" : "Genclerbirligi ",
	"team2" : "Konyaspor"
},
{
	"__v" : NumberInt("0"),
	"_id" : ObjectId("5a6a0268793ed70468152287"),
	"addedDate" : ISODate("2018-01-25T18:14:32.739+02:00"),
	"prediction" : "Home Win ",
	"resurse" : "over25tips",
	"team1" : "Santa Tecla FC ",
	"team2" : "CD Audaz"
},
{
	"__v" : NumberInt("0"),
	"_id" : ObjectId("5a6a0268793ed70468152288"),
	"addedDate" : ISODate("2018-01-25T18:14:32.739+02:00"),
	"prediction" : "Under 2.5 goals ",
	"resurse" : "over25tips",
	"team1" : "Sheffield Wednesday ",
	"team2" : "Reading"
},
{
	"__v" : NumberInt("0"),
	"_id" : ObjectId("5a6a0268793ed70468152289"),
	"addedDate" : ISODate("2018-01-25T18:14:32.740+02:00"),
	"prediction" : "Away Win ",
	"resurse" : "over25tips",
	"team1" : "Yeovil Town ",
	"team2" : "Manchester United"
},
{
	"__v" : NumberInt("0"),
	"_id" : ObjectId("5a6a0268793ed7046815228a"),
	"addedDate" : ISODate("2018-01-25T18:14:32.741+02:00"),
	"prediction" : "Home Win ",
	"resurse" : "over25tips",
	"team1" : "Pescara ",
	"team2" : "Perugia"
},
{
	"__v" : NumberInt("0"),
	"_id" : ObjectId("5a6a0268793ed7046815228b"),
	"addedDate" : ISODate("2018-01-25T18:14:32.742+02:00"),
	"prediction" : "Under 2.5 goals ",
	"resurse" : "over25tips",
	"team1" : "Trapani ",
	"team2" : "Juve Stabia"
},
{
	"__v" : NumberInt("0"),
	"_id" : ObjectId("5a6a0268793ed7046815228c"),
	"addedDate" : ISODate("2018-01-25T18:14:32.742+02:00"),
	"prediction" : "Under 2.5 goals ",
	"resurse" : "over25tips",
	"team1" : "Athletic Bilbao ",
	"team2" : "Eibar"
},
{
	"__v" : NumberInt("0"),
	"_id" : ObjectId("5a6a0268793ed7046815228d"),
	"addedDate" : ISODate("2018-01-25T18:14:32.743+02:00"),
	"prediction" : "Under 2.5 goals ",
	"resurse" : "over25tips",
	"team1" : "Zaragoza ",
	"team2" : "Cordoba"
},
{
	"__v" : NumberInt("0"),
	"_id" : ObjectId("5a6a0268793ed7046815228e"),
	"addedDate" : ISODate("2018-01-25T18:14:32.743+02:00"),
	"prediction" : "Over 2.5 goals ",
	"resurse" : "over25tips",
	"team1" : "Eintracht Frankfurt ",
	"team2" : "Borussia Moenchengladbach"
},
{
	"__v" : NumberInt("0"),
	"_id" : ObjectId("5a6a0268793ed7046815228f"),
	"addedDate" : ISODate("2018-01-25T18:14:32.744+02:00"),
	"prediction" : "Away Win ",
	"resurse" : "over25tips",
	"team1" : "Jahn Regensburg ",
	"team2" : "Ingolstadt"
},
{
	"__v" : NumberInt("0"),
	"_id" : ObjectId("5a6a0268793ed70468152290"),
	"addedDate" : ISODate("2018-01-25T18:14:32.745+02:00"),
	"prediction" : "Over 2.5 goals ",
	"resurse" : "over25tips",
	"team1" : "Union Berlin ",
	"team2" : "Nuernberg"
},
{
	"__v" : NumberInt("0"),
	"_id" : ObjectId("5a6a0268793ed70468152291"),
	"addedDate" : ISODate("2018-01-25T18:14:32.746+02:00"),
	"prediction" : "Over 2.5 goals ",
	"resurse" : "over25tips",
	"team1" : "FSV Zwickau ",
	"team2" : "Sonnenhof Grossaspach"
},
{
	"__v" : NumberInt("0"),
	"_id" : ObjectId("5a6a0268793ed70468152292"),
	"addedDate" : ISODate("2018-01-25T18:14:32.746+02:00"),
	"prediction" : "",
	"resurse" : "over25tips",
	"team1" : "Preußen Muenster ",
	"team2" : "Wuerzburger Kickers"
},
{
	"__v" : NumberInt("0"),
	"_id" : ObjectId("5a6a0268793ed70468152293"),
	"addedDate" : ISODate("2018-01-25T18:14:32.747+02:00"),
	"prediction" : "Over 2.5 goals and Btts ",
	"resurse" : "over25tips",
	"team1" : "Dijon ",
	"team2" : "Rennes"
},
{
	"__v" : NumberInt("0"),
	"_id" : ObjectId("5a6a0268793ed70468152294"),
	"addedDate" : ISODate("2018-01-25T18:14:32.748+02:00"),
	"prediction" : "Btts ",
	"resurse" : "over25tips",
	"team1" : "Auxerre ",
	"team2" : "Paris FC"
},
{
	"__v" : NumberInt("0"),
	"_id" : ObjectId("5a6a0268793ed70468152295"),
	"addedDate" : ISODate("2018-01-25T18:14:32.748+02:00"),
	"prediction" : "",
	"resurse" : "over25tips",
	"team1" : "Chateauroux ",
	"team2" : "Sochaux"
},
{
	"__v" : NumberInt("0"),
	"_id" : ObjectId("5a6a0268793ed70468152296"),
	"addedDate" : ISODate("2018-01-25T18:14:32.749+02:00"),
	"prediction" : "Over 2.5 goals ",
	"resurse" : "over25tips",
	"team1" : "Clermont Foot ",
	"team2" : "Quevilly"
},
{
	"__v" : NumberInt("0"),
	"_id" : ObjectId("5a6a0268793ed70468152297"),
	"addedDate" : ISODate("2018-01-25T18:14:32.750+02:00"),
	"prediction" : "",
	"resurse" : "over25tips",
	"team1" : "GFC Ajaccio ",
	"team2" : "Bourg en Bresse Peronnas"
},
{
	"__v" : NumberInt("0"),
	"_id" : ObjectId("5a6a0268793ed70468152298"),
	"addedDate" : ISODate("2018-01-25T18:14:32.750+02:00"),
	"prediction" : "Home Win ",
	"resurse" : "over25tips",
	"team1" : "Lens ",
	"team2" : "Orleans"
},
{
	"__v" : NumberInt("0"),
	"_id" : ObjectId("5a6a0268793ed70468152299"),
	"addedDate" : ISODate("2018-01-25T18:14:32.751+02:00"),
	"prediction" : "Over 2.5 goals ",
	"resurse" : "over25tips",
	"team1" : "Nancy ",
	"team2" : "Brest"
},
{
	"__v" : NumberInt("0"),
	"_id" : ObjectId("5a6a0268793ed7046815229a"),
	"addedDate" : ISODate("2018-01-25T18:14:32.752+02:00"),
	"prediction" : "",
	"resurse" : "over25tips",
	"team1" : "Niort ",
	"team2" : "Valenciennes"
},
{
	"__v" : NumberInt("0"),
	"_id" : ObjectId("5a6a0268793ed7046815229b"),
	"addedDate" : ISODate("2018-01-25T18:14:32.753+02:00"),
	"prediction" : "Home Win ",
	"resurse" : "over25tips",
	"team1" : "SC Heerenveen ",
	"team2" : "Sparta Rotterdam"
},
{
	"__v" : NumberInt("0"),
	"_id" : ObjectId("5a6a0268793ed7046815229c"),
	"addedDate" : ISODate("2018-01-25T18:14:32.753+02:00"),
	"prediction" : "Over 2.5 goals ",
	"resurse" : "over25tips",
	"team1" : "FC Dordrecht ",
	"team2" : "FC Oss"
},
{
	"__v" : NumberInt("0"),
	"_id" : ObjectId("5a6a0268793ed7046815229d"),
	"addedDate" : ISODate("2018-01-25T18:14:32.754+02:00"),
	"prediction" : "Over 2.5 goals ",
	"resurse" : "over25tips",
	"team1" : "Fortuna Sittard ",
	"team2" : "FC Emmen"
},
{
	"__v" : NumberInt("0"),
	"_id" : ObjectId("5a6a0268793ed7046815229e"),
	"addedDate" : ISODate("2018-01-25T18:14:32.755+02:00"),
	"prediction" : "Over 2.5 goals ",
	"resurse" : "over25tips",
	"team1" : "Helmond Sport ",
	"team2" : "Almere City FC"
},
{
	"__v" : NumberInt("0"),
	"_id" : ObjectId("5a6a0268793ed7046815229f"),
	"addedDate" : ISODate("2018-01-25T18:14:32.756+02:00"),
	"prediction" : "",
	"resurse" : "over25tips",
	"team1" : "Jong FC Utrecht ",
	"team2" : "Cambuur"
},
{
	"__v" : NumberInt("0"),
	"_id" : ObjectId("5a6a0268793ed704681522a0"),
	"addedDate" : ISODate("2018-01-25T18:14:32.758+02:00"),
	"prediction" : "Over 2.5 goals ",
	"resurse" : "over25tips",
	"team1" : "MVV Maastricht ",
	"team2" : "De Graafschap"
},
{
	"__v" : NumberInt("0"),
	"_id" : ObjectId("5a6a0268793ed704681522a1"),
	"addedDate" : ISODate("2018-01-25T18:14:32.758+02:00"),
	"prediction" : "Over 2.5 goals and Btts ",
	"resurse" : "over25tips",
	"team1" : "NEC Nijmegen ",
	"team2" : "FC Den Bosch"
},
{
	"__v" : NumberInt("0"),
	"_id" : ObjectId("5a6a0268793ed704681522a2"),
	"addedDate" : ISODate("2018-01-25T18:14:32.759+02:00"),
	"prediction" : "",
	"resurse" : "over25tips",
	"team1" : "RKC Waalwijk ",
	"team2" : "Jong Ajax"
},
{
	"__v" : NumberInt("0"),
	"_id" : ObjectId("5a6a0268793ed704681522a3"),
	"addedDate" : ISODate("2018-01-25T18:14:32.759+02:00"),
	"prediction" : "",
	"resurse" : "over25tips",
	"team1" : "Telstar ",
	"team2" : "Jong AZ Alkmaar"
},
{
	"__v" : NumberInt("0"),
	"_id" : ObjectId("5a6a0268793ed704681522a4"),
	"addedDate" : ISODate("2018-01-25T18:14:32.760+02:00"),
	"prediction" : "Home Win ",
	"resurse" : "over25tips",
	"team1" : "KV Mechelen ",
	"team2" : "Royal Excel Mouscron"
},
{
	"__v" : NumberInt("0"),
	"_id" : ObjectId("5a6a0268793ed704681522a5"),
	"addedDate" : ISODate("2018-01-25T18:14:32.761+02:00"),
	"prediction" : "Over 2.5 goals ",
	"resurse" : "over25tips",
	"team1" : "Oud-Heverlee ",
	"team2" : "Westerlo"
},
{
	"__v" : NumberInt("0"),
	"_id" : ObjectId("5a6a0268793ed704681522a6"),
	"addedDate" : ISODate("2018-01-25T18:14:32.761+02:00"),
	"prediction" : "",
	"resurse" : "over25tips",
	"team1" : "Dunfermline Athletic ",
	"team2" : "St. Mirren"
},
{
	"__v" : NumberInt("0"),
	"_id" : ObjectId("5a6a0268793ed704681522a7"),
	"addedDate" : ISODate("2018-01-25T18:14:32.762+02:00"),
	"prediction" : "Over 2.5 goals ",
	"resurse" : "over25tips",
	"team1" : "FC Krasnodar ",
	"team2" : "FC Astana"
},
{
	"__v" : NumberInt("0"),
	"_id" : ObjectId("5a6a0268793ed704681522a8"),
	"addedDate" : ISODate("2018-01-25T18:14:32.763+02:00"),
	"prediction" : "Over 2.5 goals ",
	"resurse" : "over25tips",
	"team1" : "FC Midtjylland ",
	"team2" : "Vendsyssel FF"
},
{
	"__v" : NumberInt("0"),
	"_id" : ObjectId("5a6a0268793ed704681522a9"),
	"addedDate" : ISODate("2018-01-25T18:14:32.763+02:00"),
	"prediction" : "Over 2.5 goals and Btts ",
	"resurse" : "over25tips",
	"team1" : "Slovan Liberec ",
	"team2" : "Austria Wien"
},
{
	"__v" : NumberInt("0"),
	"_id" : ObjectId("5a6a0268793ed704681522aa"),
	"addedDate" : ISODate("2018-01-25T18:14:32.764+02:00"),
	"prediction" : "Btts ",
	"resurse" : "over25tips",
	"team1" : "Ull/Kisa ",
	"team2" : "Stabaek"
},
{
	"__v" : NumberInt("0"),
	"_id" : ObjectId("5a6a0268793ed704681522ab"),
	"addedDate" : ISODate("2018-01-25T18:14:32.764+02:00"),
	"prediction" : "Over 2.5 goals ",
	"resurse" : "over25tips",
	"team1" : "SKN St. Poelten ",
	"team2" : "Tromsoe"
},
{
	"__v" : NumberInt("0"),
	"_id" : ObjectId("5a6a0268793ed704681522ac"),
	"addedDate" : ISODate("2018-01-25T18:14:32.765+02:00"),
	"prediction" : "Home Win ",
	"resurse" : "over25tips",
	"team1" : "Malmoe FF ",
	"team2" : "Flora Tallinn"
},
{
	"__v" : NumberInt("0"),
	"_id" : ObjectId("5a6a0268793ed704681522ad"),
	"addedDate" : ISODate("2018-01-25T18:14:32.765+02:00"),
	"prediction" : "Home Win ",
	"resurse" : "over25tips",
	"team1" : "VPS ",
	"team2" : "FF Jaro"
},
{
	"__v" : NumberInt("0"),
	"_id" : ObjectId("5a6a0268793ed704681522ae"),
	"addedDate" : ISODate("2018-01-25T18:14:32.766+02:00"),
	"prediction" : "",
	"resurse" : "over25tips",
	"team1" : "IF Gnistan ",
	"team2" : "HJK"
},
{
	"__v" : NumberInt("0"),
	"_id" : ObjectId("5a6a0268793ed704681522af"),
	"addedDate" : ISODate("2018-01-25T18:14:32.767+02:00"),
	"prediction" : "Over 2.5 goals ",
	"resurse" : "over25tips",
	"team1" : "Besiktas ",
	"team2" : "Kasimpasa"
},
{
	"__v" : NumberInt("0"),
	"_id" : ObjectId("5a6a0268793ed704681522b0"),
	"addedDate" : ISODate("2018-01-25T18:14:32.767+02:00"),
	"prediction" : "",
	"resurse" : "over25tips",
	"team1" : "Balikesirspor ",
	"team2" : "Erzurum BB"
},
{
	"__v" : NumberInt("0"),
	"_id" : ObjectId("5a6a0268793ed704681522b1"),
	"addedDate" : ISODate("2018-01-25T18:14:32.768+02:00"),
	"prediction" : "Over 2.5 goals ",
	"resurse" : "over25tips",
	"team1" : "Glenavon ",
	"team2" : "Warrenpoint Town"
},
{
	"__v" : NumberInt("0"),
	"_id" : ObjectId("5a6a0268793ed704681522b2"),
	"addedDate" : ISODate("2018-01-25T18:14:32.768+02:00"),
	"prediction" : "Away Win ",
	"resurse" : "over25tips",
	"team1" : "Ballinamallard United ",
	"team2" : "Cliftonville"
},
{
	"__v" : NumberInt("0"),
	"_id" : ObjectId("5a6a0268793ed704681522b3"),
	"addedDate" : ISODate("2018-01-25T18:14:32.769+02:00"),
	"prediction" : "",
	"resurse" : "over25tips",
	"team1" : "Hapoel Katamon Jerusalem ",
	"team2" : "Maccabi Herzliya"
},
{
	"__v" : NumberInt("0"),
	"_id" : ObjectId("5a6a0268793ed704681522b4"),
	"addedDate" : ISODate("2018-01-25T18:14:32.770+02:00"),
	"prediction" : "",
	"resurse" : "over25tips",
	"team1" : "Hapoel Nazareth Illit ",
	"team2" : "Hapoel Petah Tikva"
},
{
	"__v" : NumberInt("0"),
	"_id" : ObjectId("5a6a0268793ed704681522b5"),
	"addedDate" : ISODate("2018-01-25T18:14:32.771+02:00"),
	"prediction" : "",
	"resurse" : "over25tips",
	"team1" : "Hapoel Nir Ramat HaSharon ",
	"team2" : "Hapoel Rishon LeZion"
},
{
	"__v" : NumberInt("0"),
	"_id" : ObjectId("5a6a0268793ed704681522b6"),
	"addedDate" : ISODate("2018-01-25T18:14:32.772+02:00"),
	"prediction" : "Under 2.5 goals  ",
	"resurse" : "over25tips",
	"team1" : "Ironi Nesher ",
	"team2" : "Maccabi Ahi Nazareth"
},
{
	"__v" : NumberInt("0"),
	"_id" : ObjectId("5a6a0268793ed704681522b7"),
	"addedDate" : ISODate("2018-01-25T18:14:32.772+02:00"),
	"prediction" : "",
	"resurse" : "over25tips",
	"team1" : "Olimpia ",
	"team2" : "Montevideo Wanderers"
},
{
	"__v" : NumberInt("0"),
	"_id" : ObjectId("5a6a0268793ed704681522b8"),
	"addedDate" : ISODate("2018-01-25T18:14:32.773+02:00"),
	"prediction" : "Home Win  ",
	"resurse" : "over25tips",
	"team1" : "Godoy Cruz ",
	"team2" : "Chacarita Juniors"
},
{
	"__v" : NumberInt("0"),
	"_id" : ObjectId("5a6a0268793ed704681522b9"),
	"addedDate" : ISODate("2018-01-25T18:14:32.774+02:00"),
	"prediction" : "",
	"resurse" : "over25tips",
	"team1" : "Tigre ",
	"team2" : "Banfield"
},
{
	"__v" : NumberInt("0"),
	"_id" : ObjectId("5a6a0268793ed704681522ba"),
	"addedDate" : ISODate("2018-01-25T18:14:32.783+02:00"),
	"prediction" : "",
	"resurse" : "over25tips",
	"team1" : "Colo Colo ",
	"team2" : "Santiago Wanderers"
},
{
	"__v" : NumberInt("0"),
	"_id" : ObjectId("5a6a0268793ed704681522bb"),
	"addedDate" : ISODate("2018-01-25T18:14:32.784+02:00"),
	"prediction" : "Over 2.5 goals ",
	"resurse" : "over25tips",
	"team1" : "Qatar U23 ",
	"team2" : "South Korea U23"
},
{
	"__v" : NumberInt("0"),
	"_id" : ObjectId("5a6a0268793ed704681522bc"),
	"addedDate" : ISODate("2018-01-25T18:14:32.784+02:00"),
	"prediction" : "Under 2.5 goals ",
	"resurse" : "over25tips",
	"team1" : "Bengaluru FC ",
	"team2" : "Northeast United FC"
},
{
	"__v" : NumberInt("0"),
	"_id" : ObjectId("5a6a0268793ed704681522bd"),
	"addedDate" : ISODate("2018-01-25T18:14:32.785+02:00"),
	"prediction" : "Under 2.5 goals ",
	"resurse" : "over25tips",
	"team1" : "Meshki Pooshan ",
	"team2" : "Tractor Sazi Tabriz"
},
{
	"__v" : NumberInt("0"),
	"_id" : ObjectId("5a6a0268793ed704681522be"),
	"addedDate" : ISODate("2018-01-25T18:14:32.786+02:00"),
	"prediction" : "Over 2.5 goals ",
	"resurse" : "over25tips",
	"team1" : "Sepahan ",
	"team2" : "Foolad Khuzestan"
},
{
	"__v" : NumberInt("0"),
	"_id" : ObjectId("5a6a0268793ed704681522bf"),
	"addedDate" : ISODate("2018-01-25T18:14:32.786+02:00"),
	"prediction" : "",
	"resurse" : "over25tips",
	"team1" : "Paykan ",
	"team2" : "Persepolis"
},
{
	"__v" : NumberInt("0"),
	"_id" : ObjectId("5a6a0268793ed704681522c0"),
	"addedDate" : ISODate("2018-01-25T18:14:32.787+02:00"),
	"prediction" : "Btts ",
	"resurse" : "over25tips",
	"team1" : "Hatta ",
	"team2" : "Emirates Club"
},
{
	"__v" : NumberInt("0"),
	"_id" : ObjectId("5a6a0268793ed704681522c1"),
	"addedDate" : ISODate("2018-01-25T18:14:32.788+02:00"),
	"prediction" : "Over 2.5 goals ",
	"resurse" : "over25tips",
	"team1" : "Shabab Al-Ahli Dubai FC ",
	"team2" : "Al-Ain"
},
{
	"__v" : NumberInt("0"),
	"_id" : ObjectId("5a6a0268793ed704681522c2"),
	"addedDate" : ISODate("2018-01-25T18:14:32.788+02:00"),
	"prediction" : "Over 2.5 goals ",
	"resurse" : "over25tips",
	"team1" : "Melbourne Victory ",
	"team2" : "Sydney FC"
},
{
	"__v" : NumberInt("0"),
	"_id" : ObjectId("5a6a0268793ed704681522c3"),
	"addedDate" : ISODate("2018-01-25T18:14:32.789+02:00"),
	"prediction" : "Under 2.5 goals ",
	"resurse" : "over25tips",
	"team1" : "Pago Youth ",
	"team2" : "Tupapa Maraerenga FC"
},
{
	"__v" : NumberInt("0"),
	"_id" : ObjectId("5a6a0268793ed704681522c4"),
	"addedDate" : ISODate("2018-01-25T18:14:32.789+02:00"),
	"prediction" : "",
	"resurse" : "over25tips",
	"team1" : "USM Blida ",
	"team2" : "JS Saoura"
},
{
	"__v" : NumberInt("0"),
	"_id" : ObjectId("5a6a0268793ed704681522c5"),
	"addedDate" : ISODate("2018-01-25T18:14:32.791+02:00"),
	"prediction" : "Under 2.5 goals ",
	"resurse" : "over25tips",
	"team1" : "NA Hussein Dey ",
	"team2" : "MC Oran"
},
{
	"__v" : NumberInt("0"),
	"_id" : ObjectId("5a6a0268793ed704681522c6"),
	"addedDate" : ISODate("2018-01-25T18:14:32.792+02:00"),
	"prediction" : "Under 2.5 goals ",
	"resurse" : "over25tips",
	"team1" : "Paradou AC ",
	"team2" : "JS Kabylie"
},
{
	"__v" : NumberInt("0"),
	"_id" : ObjectId("5a6a0268793ed704681522c7"),
	"addedDate" : ISODate("2018-01-25T18:14:32.792+02:00"),
	"prediction" : "Under 2.5 goals ",
	"resurse" : "over25tips",
	"team1" : "USM Bel Abbes ",
	"team2" : "CS Constantine"
},
{
	"__v" : NumberInt("0"),
	"_id" : ObjectId("5a6a0268793ed704681522c8"),
	"addedDate" : ISODate("2018-01-25T18:14:32.793+02:00"),
	"prediction" : "",
	"resurse" : "over25tips",
	"team1" : "Ajax Cape Town ",
	"team2" : "Free State Stars"
},
{
	"__v" : NumberInt("0"),
	"_id" : ObjectId("5a6a0268793ed704681522c9"),
	"addedDate" : ISODate("2018-01-25T18:14:32.793+02:00"),
	"prediction" : "",
	"resurse" : "over25tips",
	"team1" : "Maritzburg United ",
	"team2" : "Chippa United"
},
{
	"__v" : NumberInt("0"),
	"_id" : ObjectId("5a6a0268793ed704681522ca"),
	"addedDate" : ISODate("2018-01-25T18:14:32.834+02:00"),
	"prediction" : "X2",
	"propability1" : "1: 28%",
	"propability2" : "2: 30%",
	"propabilityX" : "X: 42%",
	"resurse" : "zulubet",
	"team1" : "Aizawl FC",
	"team2" : "Mohun Bagan AC"
},
{
	"__v" : NumberInt("0"),
	"_id" : ObjectId("5a6a0268793ed704681522cc"),
	"addedDate" : ISODate("2018-01-25T18:14:32.842+02:00"),
	"prediction" : "1X",
	"propability1" : "1: 39%",
	"propability2" : "2: 14%",
	"propabilityX" : "X: 47%",
	"resurse" : "zulubet",
	"team1" : "Gostaresh Foolad FC",
	"team2" : "Naftoon Tehran"
},
{
	"__v" : NumberInt("0"),
	"_id" : ObjectId("5a6a0268793ed704681522cb"),
	"addedDate" : ISODate("2018-01-25T18:14:32.838+02:00"),
	"prediction" : "12",
	"propability1" : "1: 49%",
	"propability2" : "2: 33%",
	"propabilityX" : "X: 18%",
	"resurse" : "zulubet",
	"team1" : "Melbourne City FC",
	"team2" : "Newcastle United Jets"
},
{
	"__v" : NumberInt("0"),
	"_id" : ObjectId("5a6a0268793ed704681522cd"),
	"addedDate" : ISODate("2018-01-25T18:14:32.846+02:00"),
	"prediction" : "1X",
	"propability1" : "1: 42%",
	"propability2" : "2: 13%",
	"propabilityX" : "X: 45%",
	"resurse" : "zulubet",
	"team1" : "Esteghlal FC",
	"team2" : "Pars Jonoubi Jam Bushehr"
},
{
	"__v" : NumberInt("0"),
	"_id" : ObjectId("5a6a0268793ed704681522ce"),
	"addedDate" : ISODate("2018-01-25T18:14:32.850+02:00"),
	"prediction" : "1X",
	"propability1" : "1: 30%",
	"propability2" : "2: 22%",
	"propabilityX" : "X: 48%",
	"resurse" : "zulubet",
	"team1" : "Saipa Karaj FC",
	"team2" : "Radideh Mashhad"
},
{
	"__v" : NumberInt("0"),
	"_id" : ObjectId("5a6a0268793ed704681522cf"),
	"addedDate" : ISODate("2018-01-25T18:14:32.853+02:00"),
	"prediction" : "1",
	"propability1" : "1: 78%",
	"propability2" : "2: 6%",
	"propabilityX" : "X: 17%",
	"resurse" : "zulubet",
	"team1" : "FK Crvena Zvezda",
	"team2" : "FK Bask Beograd"
},
{
	"__v" : NumberInt("0"),
	"_id" : ObjectId("5a6a0268793ed704681522d0"),
	"addedDate" : ISODate("2018-01-25T18:14:32.856+02:00"),
	"prediction" : "2",
	"propability1" : "1: 13%",
	"propability2" : "2: 60%",
	"propabilityX" : "X: 27%",
	"resurse" : "zulubet",
	"team1" : "Al Ragaa",
	"team2" : "Al-Ahly Cairo"
},
{
	"__v" : NumberInt("0"),
	"_id" : ObjectId("5a6a0268793ed704681522d1"),
	"addedDate" : ISODate("2018-01-25T18:14:32.859+02:00"),
	"prediction" : "1",
	"propability1" : "1: 61%",
	"propability2" : "2: 11%",
	"propabilityX" : "X: 28%",
	"resurse" : "zulubet",
	"team1" : "Sparta Prague",
	"team2" : "Loko Vltavin"
},
{
	"__v" : NumberInt("0"),
	"_id" : ObjectId("5a6a0268793ed704681522d2"),
	"addedDate" : ISODate("2018-01-25T18:14:32.862+02:00"),
	"prediction" : "X2",
	"propability1" : "1: 30%",
	"propability2" : "2: 40%",
	"propabilityX" : "X: 30%",
	"resurse" : "zulubet",
	"team1" : "Wisla Plock",
	"team2" : "FK UFA"
},
{
	"__v" : NumberInt("0"),
	"_id" : ObjectId("5a6a0268793ed704681522d3"),
	"addedDate" : ISODate("2018-01-25T18:14:32.865+02:00"),
	"prediction" : "1",
	"propability1" : "1: 61%",
	"propability2" : "2: 19%",
	"propabilityX" : "X: 21%",
	"resurse" : "zulubet",
	"team1" : "BATE Borisov",
	"team2" : "Luch Minsk"
},
{
	"__v" : NumberInt("0"),
	"_id" : ObjectId("5a6a0268793ed704681522d4"),
	"addedDate" : ISODate("2018-01-25T18:14:32.868+02:00"),
	"prediction" : "1X",
	"propability1" : "1: 33%",
	"propability2" : "2: 21%",
	"propabilityX" : "X: 47%",
	"resurse" : "zulubet",
	"team1" : "Sanat Naft Abadan FC",
	"team2" : "Sepidrood Rasht"
},
{
	"__v" : NumberInt("0"),
	"_id" : ObjectId("5a6a0268793ed704681522d5"),
	"addedDate" : ISODate("2018-01-25T18:14:32.874+02:00"),
	"prediction" : "1X",
	"propability1" : "1: 28%",
	"propability2" : "2: 18%",
	"propabilityX" : "X: 53%",
	"resurse" : "zulubet",
	"team1" : "Misr Lel Makasa",
	"team2" : "El-Entag El-Harby"
},
{
	"__v" : NumberInt("0"),
	"_id" : ObjectId("5a6a0268793ed704681522d6"),
	"addedDate" : ISODate("2018-01-25T18:14:32.877+02:00"),
	"prediction" : "1X",
	"propability1" : "1: 40%",
	"propability2" : "2: 18%",
	"propabilityX" : "X: 42%",
	"resurse" : "zulubet",
	"team1" : "Enyimba",
	"team2" : "Nasarawa United"
},
{
	"__v" : NumberInt("0"),
	"_id" : ObjectId("5a6a0268793ed704681522d7"),
	"addedDate" : ISODate("2018-01-25T18:14:32.888+02:00"),
	"prediction" : "X",
	"propability1" : "1: 21%",
	"propability2" : "2: 23%",
	"propabilityX" : "X: 55%",
	"resurse" : "zulubet",
	"team1" : "US Biskra",
	"team2" : "ES Setif"
},
{
	"__v" : NumberInt("0"),
	"_id" : ObjectId("5a6a0268793ed704681522d8"),
	"addedDate" : ISODate("2018-01-25T18:14:32.898+02:00"),
	"prediction" : "1X",
	"propability1" : "1: 35%",
	"propability2" : "2: 15%",
	"propabilityX" : "X: 50%",
	"resurse" : "zulubet",
	"team1" : "Zenit St. Petersburg",
	"team2" : "SK Slavia Praha"
},
{
	"__v" : NumberInt("0"),
	"_id" : ObjectId("5a6a0268793ed704681522d9"),
	"addedDate" : ISODate("2018-01-25T18:14:32.900+02:00"),
	"prediction" : "X2",
	"propability1" : "1: 23%",
	"propability2" : "2: 38%",
	"propabilityX" : "X: 38%",
	"resurse" : "zulubet",
	"team1" : "Al Aqaba",
	"team2" : "Al Hussein Irbid"
},
{
	"__v" : NumberInt("0"),
	"_id" : ObjectId("5a6a0268793ed704681522da"),
	"addedDate" : ISODate("2018-01-25T18:14:32.902+02:00"),
	"prediction" : "1",
	"propability1" : "1: 56%",
	"propability2" : "2: 28%",
	"propabilityX" : "X: 16%",
	"resurse" : "zulubet",
	"team1" : "Mjondalen 2",
	"team2" : "Sandefjord Fotball"
},
{
	"__v" : NumberInt("0"),
	"_id" : ObjectId("5a6a0268793ed704681522db"),
	"addedDate" : ISODate("2018-01-25T18:14:32.906+02:00"),
	"prediction" : "12",
	"propability1" : "1: 39%",
	"propability2" : "2: 39%",
	"propabilityX" : "X: 21%",
	"resurse" : "zulubet",
	"team1" : "Tianjin Teda",
	"team2" : "Offenbacher Kickers"
},
{
	"__v" : NumberInt("0"),
	"_id" : ObjectId("5a6a0268793ed704681522dc"),
	"addedDate" : ISODate("2018-01-25T18:14:32.910+02:00"),
	"prediction" : "-46' 1",
	"propability1" : "1: 76%",
	"propability2" : "2: 14%",
	"propabilityX" : "X: 11%",
	"resurse" : "zulubet",
	"team1" : "Al Shabab KSA",
	"team2" : "Al-Khaleej"
},
{
	"__v" : NumberInt("0"),
	"_id" : ObjectId("5a6a0268793ed704681522dd"),
	"addedDate" : ISODate("2018-01-25T18:14:32.913+02:00"),
	"prediction" : "-46' 2",
	"propability1" : "1: 22%",
	"propability2" : "2: 62%",
	"propabilityX" : "X: 17%",
	"resurse" : "zulubet",
	"team1" : "Maccabi Holon FC",
	"team2" : "MS Kiryat Gat"
},
{
	"__v" : NumberInt("0"),
	"_id" : ObjectId("5a6a0268793ed704681522de"),
	"addedDate" : ISODate("2018-01-25T18:14:32.915+02:00"),
	"prediction" : "-46' 2",
	"propability1" : "1: 32%",
	"propability2" : "2: 55%",
	"propabilityX" : "X: 14%",
	"resurse" : "zulubet",
	"team1" : "Asa Tel Aviv University SC",
	"team2" : "FC Ramat Hasharon"
},
{
	"__v" : NumberInt("0"),
	"_id" : ObjectId("5a6a0268793ed704681522df"),
	"addedDate" : ISODate("2018-01-25T18:14:32.918+02:00"),
	"prediction" : "",
	"propability1" : "1: 37%",
	"propability2" : "2: 34%",
	"propabilityX" : "X: 29%",
	"resurse" : "zulubet",
	"team1" : "PAS Giannina FC",
	"team2" : "Larissa"
},
{
	"__v" : NumberInt("0"),
	"_id" : ObjectId("5a6a0268793ed704681522e0"),
	"addedDate" : ISODate("2018-01-25T18:14:32.920+02:00"),
	"prediction" : "1X",
	"propability1" : "1: 42%",
	"propability2" : "2: 25%",
	"propabilityX" : "X: 32%",
	"resurse" : "zulubet",
	"team1" : "Nova Iguacu RJ",
	"team2" : "Volta Redonda RJ"
},
{
	"__v" : NumberInt("0"),
	"_id" : ObjectId("5a6a0268793ed704681522e1"),
	"addedDate" : ISODate("2018-01-25T18:14:32.922+02:00"),
	"prediction" : "1",
	"propability1" : "1: 56%",
	"propability2" : "2: 25%",
	"propabilityX" : "X: 20%",
	"resurse" : "zulubet",
	"team1" : "Maccabi Kishronot Hadera",
	"team2" : "Hapoel Raanana"
},
{
	"__v" : NumberInt("0"),
	"_id" : ObjectId("5a6a0268793ed704681522e2"),
	"addedDate" : ISODate("2018-01-25T18:14:32.925+02:00"),
	"prediction" : "1",
	"propability1" : "1: 58%",
	"propability2" : "2: 23%",
	"propabilityX" : "X: 19%",
	"resurse" : "zulubet",
	"team1" : "Beitar Jerusalem",
	"team2" : "Hapoel Marmorek"
},
{
	"__v" : NumberInt("0"),
	"_id" : ObjectId("5a6a0268793ed704681522e3"),
	"addedDate" : ISODate("2018-01-25T18:14:32.928+02:00"),
	"prediction" : "1",
	"propability1" : "1: 71%",
	"propability2" : "2: 14%",
	"propabilityX" : "X: 15%",
	"resurse" : "zulubet",
	"team1" : "Club Brugge",
	"team2" : "KV Oostende"
},
{
	"__v" : NumberInt("0"),
	"_id" : ObjectId("5a6a0268793ed704681522e5"),
	"addedDate" : ISODate("2018-01-25T18:14:32.932+02:00"),
	"prediction" : "1X",
	"propability1" : "1: 26%",
	"propability2" : "2: 24%",
	"propabilityX" : "X: 50%",
	"resurse" : "zulubet",
	"team1" : "Racing Strasbourg",
	"team2" : "Lille OSC"
},
{
	"__v" : NumberInt("0"),
	"_id" : ObjectId("5a6a0268793ed704681522e4"),
	"addedDate" : ISODate("2018-01-25T18:14:32.930+02:00"),
	"prediction" : "1X",
	"propability1" : "1: 38%",
	"propability2" : "2: 22%",
	"propabilityX" : "X: 40%",
	"resurse" : "zulubet",
	"team1" : "Dynamo Dresden",
	"team2" : "FC St. Pauli"
},
{
	"__v" : NumberInt("0"),
	"_id" : ObjectId("5a6a0268793ed704681522e6"),
	"addedDate" : ISODate("2018-01-25T18:14:32.934+02:00"),
	"prediction" : "X2",
	"propability1" : "1: 23%",
	"propability2" : "2: 45%",
	"propabilityX" : "X: 32%",
	"resurse" : "zulubet",
	"team1" : "Bragantino SP",
	"team2" : "Sao Bento SP"
},
{
	"__v" : NumberInt("0"),
	"_id" : ObjectId("5a6a0268793ed704681522e7"),
	"addedDate" : ISODate("2018-01-25T18:14:32.936+02:00"),
	"prediction" : "1",
	"propability1" : "1: 67%",
	"propability2" : "2: 14%",
	"propabilityX" : "X: 18%",
	"resurse" : "zulubet",
	"team1" : "FC Barcelona",
	"team2" : "RCD Espanyol Barcelona"
},
{
	"__v" : NumberInt("0"),
	"_id" : ObjectId("5a6a0268793ed704681522e8"),
	"addedDate" : ISODate("2018-01-25T18:14:32.938+02:00"),
	"prediction" : "X2",
	"propability1" : "1: 21%",
	"propability2" : "2: 33%",
	"propabilityX" : "X: 47%",
	"resurse" : "zulubet",
	"team1" : "Ponte Preta SP",
	"team2" : "Santos SP"
},
{
	"__v" : NumberInt("0"),
	"_id" : ObjectId("5a6a0268793ed704681522ea"),
	"addedDate" : ISODate("2018-01-25T18:14:32.972+02:00"),
	"correctScore" : "",
	"resurse" : "bettingtips1x2",
	"team1" : ""
},
{
	"__v" : NumberInt("0"),
	"_id" : ObjectId("5a6a0268793ed704681522e9"),
	"addedDate" : ISODate("2018-01-25T18:14:32.940+02:00"),
	"prediction" : "12",
	"propability1" : "1: 50%",
	"propability2" : "2: 34%",
	"propabilityX" : "X: 17%",
	"resurse" : "zulubet",
	"team1" : "Fortaleza CE",
	"team2" : "Iguatu CE"
},
{
	"__v" : NumberInt("0"),
	"_id" : ObjectId("5a6a0268793ed704681522eb"),
	"addedDate" : ISODate("2018-01-25T18:14:32.973+02:00"),
	"correctScore" : "",
	"resurse" : "bettingtips1x2",
	"team1" : ""
},
{
	"__v" : NumberInt("0"),
	"_id" : ObjectId("5a6a0268793ed704681522ec"),
	"addedDate" : ISODate("2018-01-25T18:14:32.974+02:00"),
	"correctScore" : "",
	"resurse" : "bettingtips1x2",
	"team1" : ""
},
{
	"__v" : NumberInt("0"),
	"_id" : ObjectId("5a6a0268793ed704681522ed"),
	"addedDate" : ISODate("2018-01-25T18:14:32.974+02:00"),
	"correctScore" : "",
	"resurse" : "bettingtips1x2",
	"team1" : ""
},
{
	"__v" : NumberInt("0"),
	"_id" : ObjectId("5a6a0268793ed704681522ef"),
	"addedDate" : ISODate("2018-01-25T18:14:32.975+02:00"),
	"correctScore" : "",
	"resurse" : "bettingtips1x2",
	"team1" : ""
},
{
	"__v" : NumberInt("0"),
	"_id" : ObjectId("5a6a0268793ed704681522ee"),
	"addedDate" : ISODate("2018-01-25T18:14:32.975+02:00"),
	"correctScore" : "",
	"resurse" : "bettingtips1x2",
	"team1" : ""
},
{
	"__v" : NumberInt("0"),
	"_id" : ObjectId("5a6a0268793ed704681522f0"),
	"addedDate" : ISODate("2018-01-25T18:14:32.976+02:00"),
	"correctScore" : "",
	"resurse" : "bettingtips1x2",
	"team1" : ""
},
{
	"__v" : NumberInt("0"),
	"_id" : ObjectId("5a6a0268793ed704681522f1"),
	"addedDate" : ISODate("2018-01-25T18:14:32.977+02:00"),
	"correctScore" : "",
	"resurse" : "bettingtips1x2",
	"team1" : ""
},
{
	"__v" : NumberInt("0"),
	"_id" : ObjectId("5a6a0268793ed704681522f2"),
	"addedDate" : ISODate("2018-01-25T18:14:32.977+02:00"),
	"correctScore" : "",
	"resurse" : "bettingtips1x2",
	"team1" : ""
},
{
	"__v" : NumberInt("0"),
	"_id" : ObjectId("5a6a0268793ed704681522f3"),
	"addedDate" : ISODate("2018-01-25T18:14:32.978+02:00"),
	"correctScore" : "",
	"resurse" : "bettingtips1x2",
	"team1" : ""
},
{
	"__v" : NumberInt("0"),
	"_id" : ObjectId("5a6a0268793ed704681522f4"),
	"addedDate" : ISODate("2018-01-25T18:14:32.979+02:00"),
	"correctScore" : "0:1",
	"resurse" : "bettingtips1x2",
	"team1" : "Independiente",
	"team2" : "Rosario Central"
},
{
	"__v" : NumberInt("0"),
	"_id" : ObjectId("5a6a0268793ed704681522f5"),
	"addedDate" : ISODate("2018-01-25T18:14:32.980+02:00"),
	"correctScore" : "0:1",
	"resurse" : "bettingtips1x2",
	"team1" : "Floresta EC",
	"team2" : "Ceara CE"
},
{
	"__v" : NumberInt("0"),
	"_id" : ObjectId("5a6a0268793ed704681522f6"),
	"addedDate" : ISODate("2018-01-25T18:14:32.980+02:00"),
	"correctScore" : "0:1",
	"resurse" : "bettingtips1x2",
	"team1" : "Nautico PE",
	"team2" : "Sport Recife"
},
{
	"__v" : NumberInt("0"),
	"_id" : ObjectId("5a6a0268793ed704681522f7"),
	"addedDate" : ISODate("2018-01-25T18:14:32.981+02:00"),
	"correctScore" : "0:0",
	"resurse" : "bettingtips1x2",
	"team1" : "Sarmiento de Resistencia",
	"team2" : "CA Chaco For Ever"
},
{
	"__v" : NumberInt("0"),
	"_id" : ObjectId("5a6a0268793ed704681522f8"),
	"addedDate" : ISODate("2018-01-25T18:14:32.982+02:00"),
	"correctScore" : "0:0",
	"resurse" : "bettingtips1x2",
	"team1" : "FBC Melgar",
	"team2" : "Once Caldas"
},
{
	"__v" : NumberInt("0"),
	"_id" : ObjectId("5a6a0268793ed704681522f9"),
	"addedDate" : ISODate("2018-01-25T18:14:32.982+02:00"),
	"correctScore" : "1:3",
	"resurse" : "bettingtips1x2",
	"team1" : "Real Cartagena",
	"team2" : "Independiente Medellin"
},
{
	"__v" : NumberInt("0"),
	"_id" : ObjectId("5a6a0268793ed704681522fa"),
	"addedDate" : ISODate("2018-01-25T18:14:32.983+02:00"),
	"correctScore" : "1:2",
	"resurse" : "bettingtips1x2",
	"team1" : "Gimnasia Y Tiro",
	"team2" : "Juventud Antoniana"
},
{
	"__v" : NumberInt("0"),
	"_id" : ObjectId("5a6a0268793ed704681522fb"),
	"addedDate" : ISODate("2018-01-25T18:14:32.984+02:00"),
	"correctScore" : "2:1",
	"resurse" : "bettingtips1x2",
	"team1" : "Tampico Madero",
	"team2" : "Atlas Guadalajara"
},
{
	"__v" : NumberInt("0"),
	"_id" : ObjectId("5a6a0268793ed704681522fc"),
	"addedDate" : ISODate("2018-01-25T18:14:32.985+02:00"),
	"correctScore" : "1:1",
	"resurse" : "bettingtips1x2",
	"team1" : "Santos Laguna",
	"team2" : "Toluca"
},
{
	"__v" : NumberInt("0"),
	"_id" : ObjectId("5a6a0268793ed704681522fd"),
	"addedDate" : ISODate("2018-01-25T18:14:32.985+02:00"),
	"correctScore" : "0:3",
	"resurse" : "bettingtips1x2",
	"team1" : "Chalatenango",
	"team2" : "Fas"
},
{
	"__v" : NumberInt("0"),
	"_id" : ObjectId("5a6a0268793ed704681522ff"),
	"addedDate" : ISODate("2018-01-25T18:14:32.987+02:00"),
	"correctScore" : "0:1",
	"resurse" : "bettingtips1x2",
	"team1" : "Marathon",
	"team2" : "UPNFM"
},
{
	"__v" : NumberInt("0"),
	"_id" : ObjectId("5a6a0268793ed704681522fe"),
	"addedDate" : ISODate("2018-01-25T18:14:32.986+02:00"),
	"correctScore" : "1:0",
	"resurse" : "bettingtips1x2",
	"team1" : "Luis Angel Firpo",
	"team2" : "CD Pasaquina"
},
{
	"__v" : NumberInt("0"),
	"_id" : ObjectId("5a6a0268793ed70468152301"),
	"addedDate" : ISODate("2018-01-25T18:14:32.988+02:00"),
	"correctScore" : "0:2",
	"resurse" : "bettingtips1x2",
	"team1" : "Motagua",
	"team2" : "CD Real Sociedad"
},
{
	"__v" : NumberInt("0"),
	"_id" : ObjectId("5a6a0268793ed70468152300"),
	"addedDate" : ISODate("2018-01-25T18:14:32.988+02:00"),
	"correctScore" : "3:0",
	"resurse" : "bettingtips1x2",
	"team1" : "CD Vida",
	"team2" : "CD Platense"
},
{
	"__v" : NumberInt("0"),
	"_id" : ObjectId("5a6a0268793ed70468152302"),
	"addedDate" : ISODate("2018-01-25T18:14:32.989+02:00"),
	"correctScore" : "1:1",
	"resurse" : "bettingtips1x2",
	"team1" : "Santa Gema FC",
	"team2" : "Tauro"
},
{
	"__v" : NumberInt("0"),
	"_id" : ObjectId("5a6a0268793ed70468152303"),
	"addedDate" : ISODate("2018-01-25T18:14:32.990+02:00"),
	"correctScore" : "2:0",
	"resurse" : "bettingtips1x2",
	"team1" : "Alianza FC",
	"team2" : "Sporting San Miguelito"
},
{
	"__v" : NumberInt("0"),
	"_id" : ObjectId("5a6a0268793ed70468152304"),
	"addedDate" : ISODate("2018-01-25T18:14:32.990+02:00"),
	"correctScore" : "0:0",
	"resurse" : "bettingtips1x2",
	"team1" : "CD Honduras",
	"team2" : "Real Espana"
},
{
	"__v" : NumberInt("0"),
	"_id" : ObjectId("5a6a0268793ed70468152305"),
	"addedDate" : ISODate("2018-01-25T18:14:32.991+02:00"),
	"correctScore" : "4:0",
	"resurse" : "bettingtips1x2",
	"team1" : "Alianza FC",
	"team2" : "CD Sonsonate"
},
{
	"__v" : NumberInt("0"),
	"_id" : ObjectId("5a6a0268793ed70468152306"),
	"addedDate" : ISODate("2018-01-25T18:14:32.992+02:00"),
	"correctScore" : "4:0",
	"resurse" : "bettingtips1x2",
	"team1" : "Alajuelense",
	"team2" : "Municipal Liberia"
},
{
	"__v" : NumberInt("0"),
	"_id" : ObjectId("5a6a0268793ed70468152307"),
	"addedDate" : ISODate("2018-01-25T18:14:32.993+02:00"),
	"correctScore" : "3:1",
	"resurse" : "bettingtips1x2",
	"team1" : "Santos de Guapiles",
	"team2" : "Universidad de Costa Rica"
},
{
	"__v" : NumberInt("0"),
	"_id" : ObjectId("5a6a0268793ed70468152308"),
	"addedDate" : ISODate("2018-01-25T18:14:32.994+02:00"),
	"correctScore" : "3:1",
	"resurse" : "bettingtips1x2",
	"team1" : "Deportivo Saprissa",
	"team2" : "Municipal Grecia"
},
{
	"__v" : NumberInt("0"),
	"_id" : ObjectId("5a6a0268793ed70468152309"),
	"addedDate" : ISODate("2018-01-25T18:14:32.994+02:00"),
	"correctScore" : "1:0",
	"resurse" : "bettingtips1x2",
	"team1" : "Zeledon",
	"team2" : "Cartagines"
},
{
	"__v" : NumberInt("0"),
	"_id" : ObjectId("5a6a0268793ed7046815230a"),
	"addedDate" : ISODate("2018-01-25T18:14:32.995+02:00"),
	"correctScore" : "4:0",
	"resurse" : "bettingtips1x2",
	"team1" : "CF Monterrey",
	"team2" : "Correcaminos"
},
{
	"__v" : NumberInt("0"),
	"_id" : ObjectId("5a6a0268793ed7046815230b"),
	"addedDate" : ISODate("2018-01-25T18:14:32.996+02:00"),
	"correctScore" : "1:0",
	"resurse" : "bettingtips1x2",
	"team1" : "Unam Pumas",
	"team2" : "Juarez FC"
},
{
	"__v" : NumberInt("0"),
	"_id" : ObjectId("5a6a0268793ed7046815230c"),
	"addedDate" : ISODate("2018-01-25T18:14:32.997+02:00"),
	"correctScore" : "1:2",
	"resurse" : "bettingtips1x2",
	"team1" : "Aizawl FC",
	"team2" : "Mohun Bagan AC"
},
{
	"__v" : NumberInt("0"),
	"_id" : ObjectId("5a6a0268793ed7046815230d"),
	"addedDate" : ISODate("2018-01-25T18:14:32.997+02:00"),
	"correctScore" : "0:0",
	"resurse" : "bettingtips1x2",
	"team1" : "Melbourne City",
	"team2" : "Newcastle Jets"
},
{
	"__v" : NumberInt("0"),
	"_id" : ObjectId("5a6a0268793ed7046815230e"),
	"addedDate" : ISODate("2018-01-25T18:14:32.998+02:00"),
	"correctScore" : "1:4",
	"resurse" : "bettingtips1x2",
	"team1" : "Sheikh Russel",
	"team2" : "Abahani Limited"
},
{
	"__v" : NumberInt("0"),
	"_id" : ObjectId("5a6a0268793ed7046815230f"),
	"addedDate" : ISODate("2018-01-25T18:14:32.999+02:00"),
	"correctScore" : "1:0",
	"resurse" : "bettingtips1x2",
	"team1" : "Paide Linnameeskond",
	"team2" : "TPS"
},
{
	"__v" : NumberInt("0"),
	"_id" : ObjectId("5a6a0268793ed70468152310"),
	"addedDate" : ISODate("2018-01-25T18:14:32.999+02:00"),
	"correctScore" : "0:1",
	"resurse" : "bettingtips1x2",
	"team1" : "Hradec Kralova",
	"team2" : "MFK Frydek-Mistek"
},
{
	"__v" : NumberInt("0"),
	"_id" : ObjectId("5a6a0269793ed70468152311"),
	"addedDate" : ISODate("2018-01-25T18:14:33.000+02:00"),
	"correctScore" : "2:0",
	"resurse" : "bettingtips1x2",
	"team1" : "Guangzhou Evergrande",
	"team2" : "Copenhagen"
},
{
	"__v" : NumberInt("0"),
	"_id" : ObjectId("5a6a0269793ed70468152312"),
	"addedDate" : ISODate("2018-01-25T18:14:33.001+02:00"),
	"correctScore" : "5:0",
	"resurse" : "bettingtips1x2",
	"team1" : "Arsenal Kiev",
	"team2" : "Sumy"
},
{
	"__v" : NumberInt("0"),
	"_id" : ObjectId("5a6a0269793ed70468152313"),
	"addedDate" : ISODate("2018-01-25T18:14:33.001+02:00"),
	"correctScore" : "1:0",
	"resurse" : "bettingtips1x2",
	"team1" : "Gostaresh Foolad FC",
	"team2" : "Naft Tehran"
},
{
	"__v" : NumberInt("0"),
	"_id" : ObjectId("5a6a0269793ed70468152314"),
	"addedDate" : ISODate("2018-01-25T18:14:33.002+02:00"),
	"correctScore" : "2:0",
	"resurse" : "bettingtips1x2",
	"team1" : "São Paulo U20",
	"team2" : "Flamengo U20"
},
{
	"__v" : NumberInt("0"),
	"_id" : ObjectId("5a6a0269793ed70468152315"),
	"addedDate" : ISODate("2018-01-25T18:14:33.003+02:00"),
	"correctScore" : "1:2",
	"resurse" : "bettingtips1x2",
	"team1" : "Esteghlal",
	"team2" : "FC Pars Jonoubi Jam"
},
{
	"__v" : NumberInt("0"),
	"_id" : ObjectId("5a6a0269793ed70468152316"),
	"addedDate" : ISODate("2018-01-25T18:14:33.004+02:00"),
	"correctScore" : "1:2",
	"resurse" : "bettingtips1x2",
	"team1" : "Saipa Karaj",
	"team2" : "Esteghlal Padideh"
},
{
	"__v" : NumberInt("0"),
	"_id" : ObjectId("5a6a0269793ed70468152317"),
	"addedDate" : ISODate("2018-01-25T18:14:33.005+02:00"),
	"correctScore" : "0:2",
	"resurse" : "bettingtips1x2",
	"team1" : "Bohemians 1905",
	"team2" : "Zbrojovka Brno"
},
{
	"__v" : NumberInt("0"),
	"_id" : ObjectId("5a6a0269793ed70468152318"),
	"addedDate" : ISODate("2018-01-25T18:14:33.006+02:00"),
	"correctScore" : "1:5",
	"resurse" : "bettingtips1x2",
	"team1" : "El Raja",
	"team2" : "Al-Ahly Cairo"
},
{
	"__v" : NumberInt("0"),
	"_id" : ObjectId("5a6a0269793ed70468152319"),
	"addedDate" : ISODate("2018-01-25T18:14:33.007+02:00"),
	"correctScore" : "2:0",
	"resurse" : "bettingtips1x2",
	"team1" : "ACS Poli Timisoara",
	"team2" : "FC Ripensia Timisoara"
},
{
	"__v" : NumberInt("0"),
	"_id" : ObjectId("5a6a0269793ed7046815231b"),
	"addedDate" : ISODate("2018-01-25T18:14:33.008+02:00"),
	"correctScore" : "0:0",
	"resurse" : "bettingtips1x2",
	"team1" : "Naft Abadan",
	"team2" : "Sepidroud Rasht"
},
{
	"__v" : NumberInt("0"),
	"_id" : ObjectId("5a6a0269793ed7046815231a"),
	"addedDate" : ISODate("2018-01-25T18:14:33.008+02:00"),
	"correctScore" : "2:0",
	"resurse" : "bettingtips1x2",
	"team1" : "Sparta Prague",
	"team2" : "Loko Vltavin"
},
{
	"__v" : NumberInt("0"),
	"_id" : ObjectId("5a6a0269793ed7046815231c"),
	"addedDate" : ISODate("2018-01-25T18:14:33.009+02:00"),
	"correctScore" : "2:1",
	"resurse" : "bettingtips1x2",
	"team1" : "Atlético de Kolkata",
	"team2" : "Chennaiyin"
},
{
	"__v" : NumberInt("0"),
	"_id" : ObjectId("5a6a0269793ed7046815231d"),
	"addedDate" : ISODate("2018-01-25T18:14:33.010+02:00"),
	"correctScore" : "0:2",
	"resurse" : "bettingtips1x2",
	"team1" : "US Biskra",
	"team2" : "Setif"
},
{
	"__v" : NumberInt("0"),
	"_id" : ObjectId("5a6a0269793ed7046815231e"),
	"addedDate" : ISODate("2018-01-25T18:14:33.010+02:00"),
	"correctScore" : "1:2",
	"resurse" : "bettingtips1x2",
	"team1" : "Al Ittihad",
	"team2" : "Al-Najma Manama"
},
{
	"__v" : NumberInt("0"),
	"_id" : ObjectId("5a6a0269793ed7046815231f"),
	"addedDate" : ISODate("2018-01-25T18:14:33.011+02:00"),
	"correctScore" : "2:3",
	"resurse" : "bettingtips1x2",
	"team1" : "Frej",
	"team2" : "Dalkurd FF"
},
{
	"__v" : NumberInt("0"),
	"_id" : ObjectId("5a6a0269793ed70468152320"),
	"addedDate" : ISODate("2018-01-25T18:14:33.012+02:00"),
	"correctScore" : "1:0",
	"resurse" : "bettingtips1x2",
	"team1" : "Steaua",
	"team2" : "Admira Wacker"
},
{
	"__v" : NumberInt("0"),
	"_id" : ObjectId("5a6a0269793ed70468152321"),
	"addedDate" : ISODate("2018-01-25T18:14:33.012+02:00"),
	"correctScore" : "1:0",
	"resurse" : "bettingtips1x2",
	"team1" : "Zenit St Petersburg",
	"team2" : "Slavia Prague"
},
{
	"__v" : NumberInt("0"),
	"_id" : ObjectId("5a6a0269793ed70468152322"),
	"addedDate" : ISODate("2018-01-25T18:14:33.013+02:00"),
	"correctScore" : "2:1",
	"resurse" : "bettingtips1x2",
	"team1" : "Odd",
	"team2" : "Shanghai Shenhua"
},
{
	"__v" : NumberInt("0"),
	"_id" : ObjectId("5a6a0269793ed70468152323"),
	"addedDate" : ISODate("2018-01-25T18:14:33.014+02:00"),
	"correctScore" : "1:1",
	"resurse" : "bettingtips1x2",
	"team1" : "Misr Lel Makasa",
	"team2" : "El-Entag El-Harby"
},
{
	"__v" : NumberInt("0"),
	"_id" : ObjectId("5a6a0269793ed70468152324"),
	"addedDate" : ISODate("2018-01-25T18:14:33.014+02:00"),
	"correctScore" : "0:2",
	"resurse" : "bettingtips1x2",
	"team1" : "Mjondalen",
	"team2" : "Sandefjord BK"
},
{
	"__v" : NumberInt("0"),
	"_id" : ObjectId("5a6a0269793ed70468152325"),
	"addedDate" : ISODate("2018-01-25T18:14:33.015+02:00"),
	"correctScore" : "1:2",
	"resurse" : "bettingtips1x2",
	"team1" : "Aqaba",
	"team2" : "Al Hussein"
},
{
	"__v" : NumberInt("0"),
	"_id" : ObjectId("5a6a0269793ed70468152326"),
	"addedDate" : ISODate("2018-01-25T18:14:33.016+02:00"),
	"correctScore" : "2:1",
	"resurse" : "bettingtips1x2",
	"team1" : "Al Muharraq",
	"team2" : "Al-Riffa"
},
{
	"__v" : NumberInt("0"),
	"_id" : ObjectId("5a6a0269793ed70468152327"),
	"addedDate" : ISODate("2018-01-25T18:14:33.016+02:00"),
	"correctScore" : "1:0",
	"resurse" : "bettingtips1x2",
	"team1" : "PAS Giannina",
	"team2" : "Larissa"
},
{
	"__v" : NumberInt("0"),
	"_id" : ObjectId("5a6a0269793ed70468152328"),
	"addedDate" : ISODate("2018-01-25T18:14:33.017+02:00"),
	"correctScore" : "1:0",
	"resurse" : "bettingtips1x2",
	"team1" : "Nova Iguacu RJ",
	"team2" : "Volta Redonda"
},
{
	"__v" : NumberInt("0"),
	"_id" : ObjectId("5a6a0269793ed70468152329"),
	"addedDate" : ISODate("2018-01-25T18:14:33.018+02:00"),
	"correctScore" : "2:0",
	"resurse" : "bettingtips1x2",
	"team1" : "ASC 09 Dortmund",
	"team2" : "Westfalia Rhynern"
},
{
	"__v" : NumberInt("0"),
	"_id" : ObjectId("5a6a0269793ed7046815232a"),
	"addedDate" : ISODate("2018-01-25T18:14:33.020+02:00"),
	"correctScore" : "3:0",
	"resurse" : "bettingtips1x2",
	"team1" : "Beitar Jerusalem",
	"team2" : "Hapoel Marmorek"
},
{
	"__v" : NumberInt("0"),
	"_id" : ObjectId("5a6a0269793ed7046815232b"),
	"addedDate" : ISODate("2018-01-25T18:14:33.021+02:00"),
	"correctScore" : "0:1",
	"resurse" : "bettingtips1x2",
	"team1" : "Colchester United U23",
	"team2" : "Swansea City U23"
},
{
	"__v" : NumberInt("0"),
	"_id" : ObjectId("5a6a0269793ed7046815232c"),
	"addedDate" : ISODate("2018-01-25T18:14:33.022+02:00"),
	"correctScore" : "2:1",
	"resurse" : "bettingtips1x2",
	"team1" : "West Bromwich Albion U23",
	"team2" : "Ipswich Town U23"
},
{
	"__v" : NumberInt("0"),
	"_id" : ObjectId("5a6a0269793ed7046815232d"),
	"addedDate" : ISODate("2018-01-25T18:14:33.022+02:00"),
	"correctScore" : "1:0",
	"resurse" : "bettingtips1x2",
	"team1" : "Club Brugge",
	"team2" : "Oostende"
},
{
	"__v" : NumberInt("0"),
	"_id" : ObjectId("5a6a0269793ed7046815232e"),
	"addedDate" : ISODate("2018-01-25T18:14:33.023+02:00"),
	"correctScore" : "0:0",
	"resurse" : "bettingtips1x2",
	"team1" : "Dynamo Dresden",
	"team2" : "St Pauli"
},
{
	"__v" : NumberInt("0"),
	"_id" : ObjectId("5a6a0269793ed7046815232f"),
	"addedDate" : ISODate("2018-01-25T18:14:33.024+02:00"),
	"correctScore" : "0:0",
	"resurse" : "bettingtips1x2",
	"team1" : "Strasbourg",
	"team2" : "Lille"
},
{
	"__v" : NumberInt("0"),
	"_id" : ObjectId("5a6a0269793ed70468152330"),
	"addedDate" : ISODate("2018-01-25T18:14:33.025+02:00"),
	"correctScore" : "0:0",
	"resurse" : "bettingtips1x2",
	"team1" : "Talleres de Remedios de Escalada",
	"team2" : "Barracas Central"
},
{
	"__v" : NumberInt("0"),
	"_id" : ObjectId("5a6a0269793ed70468152331"),
	"addedDate" : ISODate("2018-01-25T18:14:33.026+02:00"),
	"correctScore" : "1:4",
	"resurse" : "bettingtips1x2",
	"team1" : "Villa Nova",
	"team2" : "Atletico Mineiro"
},
{
	"__v" : NumberInt("0"),
	"_id" : ObjectId("5a6a0269793ed70468152332"),
	"addedDate" : ISODate("2018-01-25T18:14:33.027+02:00"),
	"correctScore" : "2:1",
	"resurse" : "bettingtips1x2",
	"team1" : "Bragantino",
	"team2" : "São Bento SP"
},
{
	"__v" : NumberInt("0"),
	"_id" : ObjectId("5a6a0269793ed70468152333"),
	"addedDate" : ISODate("2018-01-25T18:14:33.028+02:00"),
	"correctScore" : "3:1",
	"resurse" : "bettingtips1x2",
	"team1" : "Barcelona",
	"team2" : "Espanyol"
},
{
	"__v" : NumberInt("0"),
	"_id" : ObjectId("5a6a0269793ed70468152334"),
	"addedDate" : ISODate("2018-01-25T18:14:33.029+02:00"),
	"correctScore" : "2:1",
	"resurse" : "bettingtips1x2",
	"team1" : "Macae Esporte RJ",
	"team2" : "Botafogo"
},
{
	"__v" : NumberInt("0"),
	"_id" : ObjectId("5a6a0269793ed70468152335"),
	"addedDate" : ISODate("2018-01-25T18:14:33.030+02:00"),
	"correctScore" : "0:2",
	"resurse" : "bettingtips1x2",
	"team1" : "EC São Luiz",
	"team2" : "Juventude RS"
},
{
	"__v" : NumberInt("0"),
	"_id" : ObjectId("5a6a0269793ed70468152336"),
	"addedDate" : ISODate("2018-01-25T18:14:33.031+02:00"),
	"correctScore" : "1:1",
	"resurse" : "bettingtips1x2",
	"team1" : "Ponte Preta",
	"team2" : "Santos"
},
{
	"__v" : NumberInt("0"),
	"_id" : ObjectId("5a6a0269793ed70468152337"),
	"addedDate" : ISODate("2018-01-25T18:14:33.031+02:00"),
	"correctScore" : "1:1",
	"resurse" : "bettingtips1x2",
	"team1" : "Ituano SP",
	"team2" : "Santo Andre SP"
},
{
	"__v" : NumberInt("0"),
	"_id" : ObjectId("5a6a0269793ed70468152338"),
	"addedDate" : ISODate("2018-01-25T18:14:33.032+02:00"),
	"correctScore" : "3:1",
	"resurse" : "bettingtips1x2",
	"team1" : "Coritiba PR",
	"team2" : "Rio Branco PR"
},
{
	"__v" : NumberInt("0"),
	"_id" : ObjectId("5a6a0269793ed70468152339"),
	"addedDate" : ISODate("2018-01-25T18:14:33.032+02:00"),
	"correctScore" : "3:1",
	"resurse" : "bettingtips1x2",
	"team1" : "Fortaleza CE",
	"team2" : "AD Iguatu"
},
{
	"__v" : NumberInt("0"),
	"_id" : ObjectId("5a6a0269793ed7046815233a"),
	"addedDate" : ISODate("2018-01-25T18:14:33.033+02:00"),
	"correctScore" : "3:0",
	"resurse" : "bettingtips1x2",
	"team1" : "Palmeiras",
	"team2" : "Red Bull Brasil SP"
},
{
	"__v" : NumberInt("0"),
	"_id" : ObjectId("5a6a0269793ed7046815233b"),
	"addedDate" : ISODate("2018-01-25T18:14:33.034+02:00"),
	"correctScore" : "2:1",
	"resurse" : "bettingtips1x2",
	"team1" : "Santa Cruz",
	"team2" : "Central PE"
},
{
	"__v" : NumberInt("0"),
	"_id" : ObjectId("5a6a0269793ed7046815233c"),
	"addedDate" : ISODate("2018-01-25T18:14:33.391+02:00"),
	"prediction" : "Under 2.5",
	"propability1" : "%50",
	"propability2" : "%19",
	"propabilityOver" : "%19",
	"propabilityUnder" : "%50",
	"propabilityX" : "%31",
	"resurse" : "betstudy",
	"team1" : "Al Shabab",
	"team2" : "Al Khaleej"
},
{
	"__v" : NumberInt("0"),
	"_id" : ObjectId("5a6a0269793ed7046815233d"),
	"addedDate" : ISODate("2018-01-25T18:14:33.396+02:00"),
	"prediction" : "Over 2.5",
	"propability1" : "%33",
	"propability2" : "%51",
	"propabilityOver" : "%51",
	"propabilityUnder" : "%83",
	"propabilityX" : "%16",
	"resurse" : "betstudy",
	"team1" : "Selbak",
	"team2" : "Fredrikstad"
},
{
	"__v" : NumberInt("0"),
	"_id" : ObjectId("5a6a0269793ed7046815233e"),
	"addedDate" : ISODate("2018-01-25T18:14:33.400+02:00"),
	"prediction" : "Over 2.5",
	"propability1" : "%61",
	"propability2" : "%32",
	"propabilityOver" : "%32",
	"propabilityUnder" : "%69",
	"propabilityX" : "%7",
	"resurse" : "betstudy",
	"team1" : "Ferencváros",
	"team2" : "Rijeka"
},
{
	"__v" : NumberInt("0"),
	"_id" : ObjectId("5a6a0269793ed70468152340"),
	"addedDate" : ISODate("2018-01-25T18:14:33.405+02:00"),
	"prediction" : "1",
	"propability1" : "%61",
	"propability2" : "%17",
	"propabilityOver" : "%17",
	"propabilityUnder" : "%55",
	"propabilityX" : "%22",
	"resurse" : "betstudy",
	"team1" : "Muharraq",
	"team2" : "Al Riffa"
},
{
	"__v" : NumberInt("0"),
	"_id" : ObjectId("5a6a0269793ed7046815233f"),
	"addedDate" : ISODate("2018-01-25T18:14:33.402+02:00"),
	"prediction" : "Over 2.5",
	"propability1" : "%38",
	"propability2" : "%51",
	"propabilityOver" : "%51",
	"propabilityUnder" : "%88",
	"propabilityX" : "%11",
	"resurse" : "betstudy",
	"team1" : "ASA Tel Aviv",
	"team2" : "Ironi Ramat HaSharon"
},
{
	"__v" : NumberInt("0"),
	"_id" : ObjectId("5a6a0269793ed70468152341"),
	"addedDate" : ISODate("2018-01-25T18:14:33.408+02:00"),
	"prediction" : "Under 2.5",
	"propability1" : "%44",
	"propability2" : "%12",
	"propabilityOver" : "%12",
	"propabilityUnder" : "%38",
	"propabilityX" : "%44",
	"resurse" : "betstudy",
	"team1" : "PAS Giannina",
	"team2" : "Larissa"
},
{
	"__v" : NumberInt("0"),
	"_id" : ObjectId("5a6a0269793ed70468152342"),
	"addedDate" : ISODate("2018-01-25T18:14:33.416+02:00"),
	"prediction" : "Over 2.5",
	"propability1" : "%47",
	"propability2" : "%42",
	"propabilityOver" : "%42",
	"propabilityUnder" : "%82",
	"propabilityX" : "%11",
	"resurse" : "betstudy",
	"team1" : "Maccabi Holon",
	"team2" : "Maccabi Kiryat Gat"
},
{
	"__v" : NumberInt("0"),
	"_id" : ObjectId("5a6a0269793ed70468152344"),
	"addedDate" : ISODate("2018-01-25T18:14:33.445+02:00"),
	"prediction" : "Over 2.5",
	"propability1" : "%73",
	"propability2" : "%1",
	"propabilityOver" : "%1",
	"propabilityUnder" : "%86",
	"propabilityX" : "%26",
	"resurse" : "betstudy",
	"team1" : "ASC 09 Dortmund",
	"team2" : "Westfalia Rhynern"
},
{
	"__v" : NumberInt("0"),
	"_id" : ObjectId("5a6a0269793ed70468152343"),
	"addedDate" : ISODate("2018-01-25T18:14:33.443+02:00"),
	"prediction" : "Under 2.5",
	"propability1" : "%37",
	"propability2" : "%13",
	"propabilityOver" : "%13",
	"propabilityUnder" : "%37",
	"propabilityX" : "%50",
	"resurse" : "betstudy",
	"team1" : "Nova Iguaçu",
	"team2" : "Volta Redonda"
},
{
	"__v" : NumberInt("0"),
	"_id" : ObjectId("5a6a0269793ed70468152345"),
	"addedDate" : ISODate("2018-01-25T18:14:33.448+02:00"),
	"prediction" : "Over 2.5",
	"propability1" : "%58",
	"propability2" : "%26",
	"propabilityOver" : "%26",
	"propabilityUnder" : "%58",
	"propabilityX" : "%16",
	"resurse" : "betstudy",
	"team1" : "Beitar Jerusalem",
	"team2" : "Hapoel Marmorek"
},
{
	"__v" : NumberInt("0"),
	"_id" : ObjectId("5a6a0269793ed70468152346"),
	"addedDate" : ISODate("2018-01-25T18:14:33.450+02:00"),
	"prediction" : "Under 2.5",
	"propability1" : "%50",
	"propability2" : "%23",
	"propabilityOver" : "%23",
	"propabilityUnder" : "%38",
	"propabilityX" : "%27",
	"resurse" : "betstudy",
	"team1" : "Itabaiana",
	"team2" : "Socorrense"
},
{
	"__v" : NumberInt("0"),
	"_id" : ObjectId("5a6a0269793ed70468152347"),
	"addedDate" : ISODate("2018-01-25T18:14:33.451+02:00"),
	"prediction" : "Over 2.5",
	"propability1" : "%41",
	"propability2" : "%34",
	"propabilityOver" : "%34",
	"propabilityUnder" : "%58",
	"propabilityX" : "%25",
	"resurse" : "betstudy",
	"team1" : "Colchester United U23",
	"team2" : "Swansea City U23"
},
{
	"__v" : NumberInt("0"),
	"_id" : ObjectId("5a6a0269793ed70468152348"),
	"addedDate" : ISODate("2018-01-25T18:14:33.453+02:00"),
	"prediction" : "2",
	"propability1" : "%7",
	"propability2" : "%63",
	"propabilityOver" : "%63",
	"propabilityUnder" : "%46",
	"propabilityX" : "%30",
	"resurse" : "betstudy",
	"team1" : "West Bromwich Albion U23",
	"team2" : "Ipswich Town U23"
},
{
	"__v" : NumberInt("0"),
	"_id" : ObjectId("5a6a0269793ed70468152349"),
	"addedDate" : ISODate("2018-01-25T18:14:33.455+02:00"),
	"prediction" : "Over 2.5",
	"propability1" : "%35",
	"propability2" : "%51",
	"propabilityOver" : "%51",
	"propabilityUnder" : "%78",
	"propabilityX" : "%14",
	"resurse" : "betstudy",
	"team1" : "Ballymena United U20",
	"team2" : "Ards U20"
},
{
	"__v" : NumberInt("0"),
	"_id" : ObjectId("5a6a0269793ed7046815234a"),
	"addedDate" : ISODate("2018-01-25T18:14:33.457+02:00"),
	"prediction" : "1",
	"propability1" : "%72",
	"propability2" : "%12",
	"propabilityOver" : "%12",
	"propabilityUnder" : "%55",
	"propabilityX" : "%16",
	"resurse" : "betstudy",
	"team1" : "Club Brugge",
	"team2" : "KV Oostende"
},
{
	"__v" : NumberInt("0"),
	"_id" : ObjectId("5a6a0269793ed7046815234b"),
	"addedDate" : ISODate("2018-01-25T18:14:33.460+02:00"),
	"prediction" : "Over 2.5",
	"propability1" : "%50",
	"propability2" : "%34",
	"propabilityOver" : "%34",
	"propabilityUnder" : "%55",
	"propabilityX" : "%16",
	"resurse" : "betstudy",
	"team1" : "Dynamo Dresden",
	"team2" : "St. Pauli"
},
{
	"__v" : NumberInt("0"),
	"_id" : ObjectId("5a6a0269793ed7046815234c"),
	"addedDate" : ISODate("2018-01-25T18:14:33.462+02:00"),
	"prediction" : "Over 2.5",
	"propability1" : "%37",
	"propability2" : "%38",
	"propabilityOver" : "%38",
	"propabilityUnder" : "%81",
	"propabilityX" : "%25",
	"resurse" : "betstudy",
	"team1" : "Valur U19",
	"team2" : "Fjölnir U19"
},
{
	"__v" : NumberInt("0"),
	"_id" : ObjectId("5a6a0269793ed7046815234d"),
	"addedDate" : ISODate("2018-01-25T18:14:33.464+02:00"),
	"prediction" : "2",
	"propability1" : "%27",
	"propability2" : "%57",
	"propabilityOver" : "%57",
	"propabilityUnder" : "%50",
	"propabilityX" : "%16",
	"resurse" : "betstudy",
	"team1" : "FH",
	"team2" : "Breidablik"
},
{
	"__v" : NumberInt("0"),
	"_id" : ObjectId("5a6a0269793ed7046815234e"),
	"addedDate" : ISODate("2018-01-25T18:14:33.466+02:00"),
	"prediction" : "Under 2.5",
	"propability1" : "%50",
	"propability2" : "%23",
	"propabilityOver" : "%23",
	"propabilityUnder" : "%27",
	"propabilityX" : "%27",
	"resurse" : "betstudy",
	"team1" : "Montego Bay United",
	"team2" : "Harbour View"
},
{
	"__v" : NumberInt("0"),
	"_id" : ObjectId("5a6a0269793ed7046815234f"),
	"addedDate" : ISODate("2018-01-25T18:14:33.468+02:00"),
	"prediction" : "Over 2.5",
	"propability1" : "%50",
	"propability2" : "%45",
	"propabilityOver" : "%45",
	"propabilityUnder" : "%66",
	"propabilityX" : "%5",
	"resurse" : "betstudy",
	"team1" : "Strasbourg",
	"team2" : "Lille"
},
{
	"__v" : NumberInt("0"),
	"_id" : ObjectId("5a6a0269793ed70468152350"),
	"addedDate" : ISODate("2018-01-25T18:14:33.470+02:00"),
	"prediction" : "Over 2.5",
	"propability1" : "%44",
	"propability2" : "%18",
	"propabilityOver" : "%18",
	"propabilityUnder" : "%55",
	"propabilityX" : "%38",
	"resurse" : "betstudy",
	"team1" : "Dergview",
	"team2" : "Loughgall"
},
{
	"__v" : NumberInt("0"),
	"_id" : ObjectId("5a6a0269793ed70468152351"),
	"addedDate" : ISODate("2018-01-25T18:14:33.472+02:00"),
	"prediction" : "Under 2.5",
	"propability1" : "%53",
	"propability2" : "%14",
	"propabilityOver" : "%14",
	"propabilityUnder" : "%40",
	"propabilityX" : "%33",
	"resurse" : "betstudy",
	"team1" : "Talleres Remedios",
	"team2" : "Barracas Central"
},
{
	"__v" : NumberInt("0"),
	"_id" : ObjectId("5a6a0269793ed70468152352"),
	"addedDate" : ISODate("2018-01-25T18:14:33.474+02:00"),
	"prediction" : "Under 2.5",
	"propability1" : "%26",
	"propability2" : "%28",
	"propabilityOver" : "%28",
	"propabilityUnder" : "%13",
	"propabilityX" : "%46",
	"resurse" : "betstudy",
	"team1" : "Bragantino",
	"team2" : "São Bento"
},
{
	"__v" : NumberInt("0"),
	"_id" : ObjectId("5a6a0269793ed70468152353"),
	"addedDate" : ISODate("2018-01-25T18:14:33.475+02:00"),
	"prediction" : "Over 2.5",
	"propability1" : "%27",
	"propability2" : "%46",
	"propabilityOver" : "%46",
	"propabilityUnder" : "%55",
	"propabilityX" : "%27",
	"resurse" : "betstudy",
	"team1" : "Villa Nova",
	"team2" : "Atlético Mineiro"
},
{
	"__v" : NumberInt("0"),
	"_id" : ObjectId("5a6a0269793ed70468152354"),
	"addedDate" : ISODate("2018-01-25T18:14:33.477+02:00"),
	"prediction" : "Over 2.5",
	"propability1" : "%66",
	"propability2" : "%18",
	"propabilityOver" : "%18",
	"propabilityUnder" : "%66",
	"propabilityX" : "%16",
	"resurse" : "betstudy",
	"team1" : "Barcelona",
	"team2" : "Espanyol"
},
{
	"__v" : NumberInt("0"),
	"_id" : ObjectId("5a6a0269793ed70468152355"),
	"addedDate" : ISODate("2018-01-25T18:14:33.480+02:00"),
	"prediction" : "Under 2.5",
	"propability1" : "%25",
	"propability2" : "%32",
	"propabilityOver" : "%32",
	"propabilityUnder" : "%50",
	"propabilityX" : "%43",
	"resurse" : "betstudy",
	"team1" : "Macaé",
	"team2" : "Botafogo"
},
{
	"__v" : NumberInt("0"),
	"_id" : ObjectId("5a6a0269793ed70468152356"),
	"addedDate" : ISODate("2018-01-25T18:14:33.482+02:00"),
	"prediction" : "1",
	"propability1" : "%68",
	"propability2" : "%14",
	"propabilityOver" : "%14",
	"propabilityUnder" : "%37",
	"propabilityX" : "%18",
	"resurse" : "betstudy",
	"team1" : "São Luiz",
	"team2" : "Juventude"
},
{
	"__v" : NumberInt("0"),
	"_id" : ObjectId("5a6a0269793ed70468152357"),
	"addedDate" : ISODate("2018-01-25T18:14:33.484+02:00"),
	"prediction" : "Over 2.5",
	"propability1" : "%44",
	"propability2" : "%45",
	"propabilityOver" : "%45",
	"propabilityUnder" : "%55",
	"propabilityX" : "%11",
	"resurse" : "betstudy",
	"team1" : "Ponte Preta",
	"team2" : "Santos"
},
{
	"__v" : NumberInt("0"),
	"_id" : ObjectId("5a6a0269793ed70468152358"),
	"addedDate" : ISODate("2018-01-25T18:14:33.486+02:00"),
	"prediction" : "Under 2.5",
	"propability1" : "%44",
	"propability2" : "%23",
	"propabilityOver" : "%23",
	"propabilityUnder" : "%50",
	"propabilityX" : "%33",
	"resurse" : "betstudy",
	"team1" : "Ituano",
	"team2" : "Santo André"
},
{
	"__v" : NumberInt("0"),
	"_id" : ObjectId("5a6a0269793ed70468152359"),
	"addedDate" : ISODate("2018-01-25T18:14:33.488+02:00"),
	"prediction" : "Over 2.5",
	"propability1" : "%38",
	"propability2" : "%51",
	"propabilityOver" : "%51",
	"propabilityUnder" : "%55",
	"propabilityX" : "%11",
	"resurse" : "betstudy",
	"team1" : "Dakota",
	"team2" : "Estrella"
},
{
	"__v" : NumberInt("0"),
	"_id" : ObjectId("5a6a0269793ed7046815235a"),
	"addedDate" : ISODate("2018-01-25T18:14:33.491+02:00"),
	"prediction" : "1",
	"propability1" : "%72",
	"propability2" : "%6",
	"propabilityOver" : "%6",
	"propabilityUnder" : "%61",
	"propabilityX" : "%22",
	"resurse" : "betstudy",
	"team1" : "Coritiba",
	"team2" : "Rio Branco PR"
},
{
	"__v" : NumberInt("0"),
	"_id" : ObjectId("5a6a0269793ed7046815235b"),
	"addedDate" : ISODate("2018-01-25T18:14:33.493+02:00"),
	"prediction" : "Over 2.5",
	"propability1" : "%58",
	"propability2" : "%17",
	"propabilityOver" : "%17",
	"propabilityUnder" : "%75",
	"propabilityX" : "%25",
	"resurse" : "betstudy",
	"team1" : "Paraguay U20",
	"team2" : "Venezuela U20"
},
{
	"__v" : NumberInt("0"),
	"_id" : ObjectId("5a6a0269793ed7046815235c"),
	"addedDate" : ISODate("2018-01-25T18:14:33.496+02:00"),
	"prediction" : "Over 2.5",
	"propability1" : "%55",
	"propability2" : "%12",
	"propabilityOver" : "%12",
	"propabilityUnder" : "%55",
	"propabilityX" : "%33",
	"resurse" : "betstudy",
	"team1" : "Santa Cruz",
	"team2" : "Central"
},
{
	"__v" : NumberInt("0"),
	"_id" : ObjectId("5a6a0269793ed7046815235e"),
	"addedDate" : ISODate("2018-01-25T18:14:33.502+02:00"),
	"prediction" : "Under 2.5",
	"propability1" : "%61",
	"propability2" : "%16",
	"propabilityOver" : "%16",
	"propabilityUnder" : "%38",
	"propabilityX" : "%23",
	"resurse" : "betstudy",
	"team1" : "Palmeiras",
	"team2" : "RB Brasil"
},
{
	"__v" : NumberInt("0"),
	"_id" : ObjectId("5a6a0269793ed7046815235d"),
	"addedDate" : ISODate("2018-01-25T18:14:33.499+02:00"),
	"prediction" : "Over 2.5",
	"propability1" : "%33",
	"propability2" : "%51",
	"propabilityOver" : "%51",
	"propabilityUnder" : "%66",
	"propabilityX" : "%16",
	"resurse" : "betstudy",
	"team1" : "Deva Boys",
	"team2" : "Flora"
},
{
	"__v" : NumberInt("0"),
	"_id" : ObjectId("5a6a0269793ed7046815235f"),
	"addedDate" : ISODate("2018-01-25T18:14:33.505+02:00"),
	"prediction" : "1",
	"propability1" : "%63",
	"propability2" : "%10",
	"propabilityOver" : "%10",
	"propabilityUnder" : "%45",
	"propabilityX" : "%27",
	"resurse" : "betstudy",
	"team1" : "ASSU",
	"team2" : "Força e Luz"
},
{
	"__v" : NumberInt("0"),
	"_id" : ObjectId("5a6a0269793ed70468152361"),
	"addedDate" : ISODate("2018-01-25T18:14:33.510+02:00"),
	"prediction" : "1",
	"propability1" : "%61",
	"propability2" : "%12",
	"propabilityOver" : "%12",
	"propabilityUnder" : "%44",
	"propabilityX" : "%27",
	"resurse" : "betstudy",
	"team1" : "Matoury",
	"team2" : "Remire"
},
{
	"__v" : NumberInt("0"),
	"_id" : ObjectId("5a6a0269793ed70468152360"),
	"addedDate" : ISODate("2018-01-25T18:14:33.508+02:00"),
	"prediction" : "Under 2.5",
	"propability1" : "%38",
	"propability2" : "%32",
	"propabilityOver" : "%32",
	"propabilityUnder" : "%38",
	"propabilityX" : "%30",
	"resurse" : "betstudy",
	"team1" : "Globo",
	"team2" : "Santa Cruz de Natal RN"
},
{
	"__v" : NumberInt("0"),
	"_id" : ObjectId("5a6a026a793ed70468152364"),
	"addedDate" : ISODate("2018-01-25T18:14:34.118+02:00"),
	"correctScore" : "2-0",
	"prediction" : "",
	"propability1" : "65 %",
	"propability2" : "15 %",
	"propabilityOver" : "",
	"propabilityUnder" : "",
	"propabilityX" : "20 %",
	"resurse" : "iambettor",
	"team1" : "Club Brugge KV",
	"team2" : "KV Oostende"
},
{
	"__v" : NumberInt("0"),
	"_id" : ObjectId("5a6a0269793ed70468152363"),
	"addedDate" : ISODate("2018-01-25T18:14:33.513+02:00"),
	"prediction" : "Under 2.5",
	"propability1" : "%18",
	"propability2" : "%45",
	"propabilityOver" : "%45",
	"propabilityUnder" : "%31",
	"propabilityX" : "%37",
	"resurse" : "betstudy",
	"team1" : "Dom Bosco",
	"team2" : "Cuiabá"
},
{
	"__v" : NumberInt("0"),
	"_id" : ObjectId("5a6a026a793ed70468152366"),
	"addedDate" : ISODate("2018-01-25T18:14:34.124+02:00"),
	"correctScore" : "2-2",
	"prediction" : "",
	"propability1" : "41 %",
	"propability2" : "28 %",
	"propabilityOver" : "",
	"propabilityUnder" : "",
	"propabilityX" : "31 %",
	"resurse" : "iambettor",
	"team1" : "Melbourne Heart",
	"team2" : "Newcastle Jets"
},
{
	"__v" : NumberInt("0"),
	"_id" : ObjectId("5a6a0269793ed70468152362"),
	"addedDate" : ISODate("2018-01-25T18:14:33.511+02:00"),
	"prediction" : "Under 2.5",
	"propability1" : "%35",
	"propability2" : "%30",
	"propabilityOver" : "%30",
	"propabilityUnder" : "%50",
	"propabilityX" : "%35",
	"resurse" : "betstudy",
	"team1" : "Fortaleza",
	"team2" : "Iguatu"
},
{
	"__v" : NumberInt("0"),
	"_id" : ObjectId("5a6a026a793ed70468152365"),
	"addedDate" : ISODate("2018-01-25T18:14:34.120+02:00"),
	"correctScore" : "2-1",
	"prediction" : "",
	"propability1" : "53 %",
	"propability2" : "22 %",
	"propabilityOver" : "",
	"propabilityUnder" : "",
	"propabilityX" : "26 %",
	"resurse" : "iambettor",
	"team1" : "1. FC Dynamo Dresden",
	"team2" : "FC St. Pauli 1910"
},
{
	"__v" : NumberInt("0"),
	"_id" : ObjectId("5a6a026a793ed70468152369"),
	"addedDate" : ISODate("2018-01-25T18:14:34.433+02:00"),
	"avarageGoal" : "1.43",
	"correctScore" : "1 - 1",
	"prediction" : "X",
	"propability1" : "30",
	"propability2" : "34",
	"propabilityX" : "36",
	"resurse" : "Forebet",
	"team1" : "Masr lel Maqassah",
	"team2" : "Al Intagh Al Harbi"
},
{
	"__v" : NumberInt("0"),
	"_id" : ObjectId("5a6a026a793ed70468152368"),
	"addedDate" : ISODate("2018-01-25T18:14:34.432+02:00"),
	"avarageGoal" : "1.38",
	"correctScore" : "0 - 1",
	"prediction" : "2",
	"propability1" : "22",
	"propability2" : "46",
	"propabilityX" : "32",
	"resurse" : "Forebet",
	"team1" : "US Biskra",
	"team2" : "ES S&#xE9;tif"
},
{
	"__v" : NumberInt("0"),
	"_id" : ObjectId("5a6a026a793ed70468152367"),
	"addedDate" : ISODate("2018-01-25T18:14:34.431+02:00"),
	"avarageGoal" : "2.67",
	"correctScore" : "1 - 2",
	"prediction" : "2",
	"propability1" : "26",
	"propability2" : "42",
	"propabilityX" : "31",
	"resurse" : "Forebet",
	"team1" : "ATK",
	"team2" : "Chennaiyin"
},
{
	"__v" : NumberInt("0"),
	"_id" : ObjectId("5a6a026a793ed7046815236b"),
	"addedDate" : ISODate("2018-01-25T18:14:34.435+02:00"),
	"avarageGoal" : "2.88",
	"correctScore" : "1 - 1",
	"prediction" : "X",
	"propability1" : "17",
	"propability2" : "33",
	"propabilityX" : "50",
	"resurse" : "Forebet",
	"team1" : "Al Aqaba SC",
	"team2" : "Hussein Irbid"
},
{
	"__v" : NumberInt("0"),
	"_id" : ObjectId("5a6a026a793ed7046815236a"),
	"addedDate" : ISODate("2018-01-25T18:14:34.434+02:00"),
	"avarageGoal" : "1.43",
	"correctScore" : "1 - 0",
	"prediction" : "1",
	"propability1" : "46",
	"propability2" : "23",
	"propabilityX" : "31",
	"resurse" : "Forebet",
	"team1" : "Enyimba",
	"team2" : "Nasarawa Utd"
},
{
	"__v" : NumberInt("0"),
	"_id" : ObjectId("5a6a026a793ed7046815236e"),
	"addedDate" : ISODate("2018-01-25T18:14:34.439+02:00"),
	"avarageGoal" : "3.57",
	"correctScore" : "3 - 1",
	"prediction" : "1",
	"propability1" : "66",
	"propability2" : "14",
	"propabilityX" : "21",
	"resurse" : "Forebet",
	"team1" : "Club Brugge",
	"team2" : "KV Oostende"
},
{
	"__v" : NumberInt("0"),
	"_id" : ObjectId("5a6a026a793ed7046815236d"),
	"addedDate" : ISODate("2018-01-25T18:14:34.438+02:00"),
	"avarageGoal" : "3.72",
	"correctScore" : "2 - 2",
	"prediction" : "X",
	"propability1" : "32",
	"propability2" : "33",
	"propabilityX" : "34",
	"resurse" : "Forebet",
	"team1" : "Dynamo Dresden",
	"team2" : "St. Pauli"
},
{
	"__v" : NumberInt("0"),
	"_id" : ObjectId("5a6a026a793ed7046815236c"),
	"addedDate" : ISODate("2018-01-25T18:14:34.437+02:00"),
	"avarageGoal" : "3.74",
	"correctScore" : "2 - 3",
	"prediction" : "2",
	"propability1" : "25",
	"propability2" : "43",
	"propabilityX" : "32",
	"resurse" : "Forebet",
	"team1" : "Gharrafa SC",
	"team2" : "Al Sadd SC"
},
{
	"__v" : NumberInt("0"),
	"_id" : ObjectId("5a6a026a793ed70468152370"),
	"addedDate" : ISODate("2018-01-25T18:14:34.441+02:00"),
	"avarageGoal" : "1.33",
	"correctScore" : "1 - 1",
	"prediction" : "X",
	"propability1" : "39",
	"propability2" : "19",
	"propabilityX" : "42",
	"resurse" : "Forebet",
	"team1" : "Talleres (RdE)",
	"team2" : "Barracas Central"
},
{
	"__v" : NumberInt("0"),
	"_id" : ObjectId("5a6a026a793ed7046815236f"),
	"addedDate" : ISODate("2018-01-25T18:14:34.440+02:00"),
	"avarageGoal" : "2.97",
	"correctScore" : "2 - 1",
	"prediction" : "1",
	"propability1" : "39",
	"propability2" : "30",
	"propabilityX" : "31",
	"resurse" : "Forebet",
	"team1" : "Strasbourg",
	"team2" : "Lille OSC"
},
{
	"__v" : NumberInt("0"),
	"_id" : ObjectId("5a6a026a793ed70468152372"),
	"addedDate" : ISODate("2018-01-25T18:14:34.443+02:00"),
	"avarageGoal" : "3.38",
	"correctScore" : "3 - 1",
	"prediction" : "1",
	"propability1" : "59",
	"propability2" : "17",
	"propabilityX" : "24",
	"resurse" : "Forebet",
	"team1" : "Santa Tecla",
	"team2" : "CD Audaz"
},
{
	"__v" : NumberInt("0"),
	"_id" : ObjectId("5a6a026a793ed70468152373"),
	"addedDate" : ISODate("2018-01-25T18:14:34.444+02:00"),
	"avarageGoal" : "1.88",
	"correctScore" : "1 - 2",
	"prediction" : "2",
	"propability1" : "33",
	"propability2" : "38",
	"propabilityX" : "30",
	"resurse" : "Forebet",
	"team1" : "Sanat Naft AC",
	"team2" : "Sepidrood Rasht"
},
{
	"__v" : NumberInt("0"),
	"_id" : ObjectId("5a6a026a793ed70468152371"),
	"addedDate" : ISODate("2018-01-25T18:14:34.442+02:00"),
	"avarageGoal" : "2.95",
	"correctScore" : "3 - 0",
	"prediction" : "1",
	"propability1" : "53",
	"propability2" : "22",
	"propabilityX" : "25",
	"resurse" : "Forebet",
	"team1" : "FC Barcelona",
	"team2" : "RCD Espanyol"
},
{
	"__v" : NumberInt("0"),
	"_id" : ObjectId("5a6a026a793ed70468152375"),
	"addedDate" : ISODate("2018-01-25T18:14:34.460+02:00"),
	"avarageGoal" : "2.67",
	"correctScore" : "2 - 1",
	"prediction" : "1",
	"propability1" : "39",
	"propability2" : "22",
	"propabilityX" : "38",
	"resurse" : "Forebet",
	"team1" : "Saipa Karaj",
	"team2" : "Padideh Shandiz"
},
{
	"__v" : NumberInt("0"),
	"_id" : ObjectId("5a6a026a793ed70468152374"),
	"addedDate" : ISODate("2018-01-25T18:14:34.459+02:00"),
	"avarageGoal" : "2.70",
	"correctScore" : "0 - 3",
	"prediction" : "2",
	"propability1" : "12",
	"propability2" : "68",
	"propabilityX" : "20",
	"resurse" : "Forebet",
	"team1" : "Al Raja",
	"team2" : "Ahly Cairo"
},
{
	"__v" : NumberInt("0"),
	"_id" : ObjectId("5a6a026a793ed70468152378"),
	"addedDate" : ISODate("2018-01-25T18:14:34.464+02:00"),
	"avarageGoal" : "3.90",
	"correctScore" : "3 - 2",
	"prediction" : "1",
	"propability1" : "40",
	"propability2" : "33",
	"propabilityX" : "28",
	"resurse" : "Forebet",
	"team1" : "Melbourne City",
	"team2" : "Newcastle Jets"
},
{
	"__v" : NumberInt("0"),
	"_id" : ObjectId("5a6a026a793ed70468152377"),
	"addedDate" : ISODate("2018-01-25T18:14:34.463+02:00"),
	"avarageGoal" : "1.50",
	"correctScore" : "1 - 1",
	"prediction" : "X",
	"propability1" : "37",
	"propability2" : "26",
	"propabilityX" : "38",
	"resurse" : "Forebet",
	"team1" : "Gostaresh Foolad",
	"team2" : "Naft Tehran"
},
{
	"__v" : NumberInt("0"),
	"_id" : ObjectId("5a6a026a793ed70468152379"),
	"addedDate" : ISODate("2018-01-25T18:14:34.465+02:00"),
	"avarageGoal" : "2.17",
	"correctScore" : "2 - 0",
	"prediction" : "1",
	"propability1" : "38",
	"propability2" : "37",
	"propabilityX" : "25",
	"resurse" : "Forebet",
	"team1" : "Aizawl FC",
	"team2" : "Mohun Bagan AC"
},
{
	"__v" : NumberInt("0"),
	"_id" : ObjectId("5a6a026a793ed70468152376"),
	"addedDate" : ISODate("2018-01-25T18:14:34.462+02:00"),
	"avarageGoal" : "2.00",
	"correctScore" : "1 - 1",
	"prediction" : "X",
	"propability1" : "21",
	"propability2" : "34",
	"propabilityX" : "45",
	"resurse" : "Forebet",
	"team1" : "Esteghlal Tehran",
	"team2" : "Pars Jonoubi Jam"
},
{
	"__v" : NumberInt("0"),
	"_id" : ObjectId("5a6a026a793ed7046815237a"),
	"addedDate" : ISODate("2018-01-25T18:14:34.466+02:00"),
	"avarageGoal" : "3.63",
	"correctScore" : "3 - 1",
	"prediction" : "1",
	"propability1" : "61",
	"propability2" : "15",
	"propabilityX" : "23",
	"resurse" : "Forebet",
	"team1" : "Saprissa",
	"team2" : "Municipal Grecia"
},
{
	"__v" : NumberInt("0"),
	"_id" : ObjectId("5a6a026a793ed7046815237c"),
	"addedDate" : ISODate("2018-01-25T18:14:34.478+02:00"),
	"avarageGoal" : "2.96",
	"correctScore" : "3 - 1",
	"prediction" : "1",
	"propability1" : "46",
	"propability2" : "23",
	"propabilityX" : "31",
	"resurse" : "Forebet",
	"team1" : "P&#xE9;rez Zeled&#xF3;n",
	"team2" : "CS Cartagin&#xE9;s"
},
{
	"__v" : NumberInt("0"),
	"_id" : ObjectId("5a6a026a793ed7046815237d"),
	"addedDate" : ISODate("2018-01-25T18:14:34.479+02:00"),
	"avarageGoal" : "2.73",
	"correctScore" : "3 - 1",
	"prediction" : "1",
	"propability1" : "57",
	"propability2" : "19",
	"propabilityX" : "23",
	"resurse" : "Forebet",
	"team1" : "LD Alajuelense",
	"team2" : "Municipal Liberia"
},
{
	"__v" : NumberInt("0"),
	"_id" : ObjectId("5a6a026a793ed7046815237e"),
	"addedDate" : ISODate("2018-01-25T18:14:34.480+02:00"),
	"avarageGoal" : "3.50",
	"correctScore" : "3 - 1",
	"prediction" : "1",
	"propability1" : "63",
	"propability2" : "3",
	"propabilityX" : "34",
	"resurse" : "Forebet",
	"team1" : "Alianza FC",
	"team2" : "Sonsonate FC"
},
{
	"__v" : NumberInt("0"),
	"_id" : ObjectId("5a6a026a793ed7046815237b"),
	"addedDate" : ISODate("2018-01-25T18:14:34.477+02:00"),
	"avarageGoal" : "2.25",
	"correctScore" : "2 - 0",
	"prediction" : "1",
	"propability1" : "46",
	"propability2" : "21",
	"propabilityX" : "33",
	"resurse" : "Forebet",
	"team1" : "Santos Gu&#xE1;piles",
	"team2" : "Universidad CR"
},
{
	"__v" : NumberInt("0"),
	"_id" : ObjectId("5a6a026a793ed7046815237f"),
	"addedDate" : ISODate("2018-01-25T18:14:34.480+02:00"),
	"avarageGoal" : "1.83",
	"correctScore" : "1 - 1",
	"prediction" : "X",
	"propability1" : "33",
	"propability2" : "19",
	"propabilityX" : "49",
	"resurse" : "Forebet",
	"team1" : "Lu&#xED;s &#xC1;ngel Firpo",
	"team2" : "CD Pasaquina"
},
{
	"__v" : NumberInt("0"),
	"_id" : ObjectId("5a6a026a793ed70468152381"),
	"addedDate" : ISODate("2018-01-25T18:14:34.482+02:00"),
	"avarageGoal" : "2.28",
	"correctScore" : "1 - 1",
	"prediction" : "X",
	"propability1" : "18",
	"propability2" : "37",
	"propabilityX" : "45",
	"resurse" : "Forebet",
	"team1" : "CD Dragon",
	"team2" : "CD &#xC1;guila"
},
{
	"__v" : NumberInt("0"),
	"_id" : ObjectId("5a6a026a793ed70468152380"),
	"addedDate" : ISODate("2018-01-25T18:14:34.481+02:00"),
	"avarageGoal" : "2.06",
	"correctScore" : "0 - 0",
	"prediction" : "X",
	"propability1" : "22",
	"propability2" : "30",
	"propabilityX" : "48",
	"resurse" : "Forebet",
	"team1" : "CD Chalatenango",
	"team2" : "CD FAS"
},
{
	"__v" : NumberInt("0"),
	"_id" : ObjectId("5a6a026a793ed70468152383"),
	"addedDate" : ISODate("2018-01-25T18:14:34.483+02:00"),
	"avarageGoal" : "1.96",
	"correctScore" : "1 - 1",
	"prediction" : "X",
	"propability1" : "30",
	"propability2" : "34",
	"propabilityX" : "36",
	"resurse" : "Forebet",
	"team1" : "Municipal Lime&#xF1;o",
	"team2" : "Isidro Metap&#xE1;n"
},
{
	"__v" : NumberInt("0"),
	"_id" : ObjectId("5a6a026a793ed70468152382"),
	"addedDate" : ISODate("2018-01-25T18:14:34.482+02:00"),
	"avarageGoal" : "1.92",
	"correctScore" : "1 - 0",
	"prediction" : "1",
	"propability1" : "46",
	"propability2" : "19",
	"propabilityX" : "34",
	"resurse" : "Forebet",
	"team1" : "Independiente",
	"team2" : "Rosario Central"
},
{
	"__v" : NumberInt("0"),
	"_id" : ObjectId("5a6a026a793ed70468152384"),
	"addedDate" : ISODate("2018-01-25T18:14:34.483+02:00"),
	"avarageGoal" : "2.50",
	"correctScore" : "2 - 1",
	"prediction" : "1",
	"propability1" : "37",
	"propability2" : "35",
	"propabilityX" : "28",
	"resurse" : "Forebet",
	"team1" : "Lim&#xF3;n FC",
	"team2" : "AD Carmelita"
},
{
	"__v" : NumberInt("0"),
	"_id" : ObjectId("5a6a026a793ed70468152385"),
	"addedDate" : ISODate("2018-01-25T18:14:34.484+02:00"),
	"avarageGoal" : "0.87",
	"correctScore" : "0 - 1",
	"prediction" : "2",
	"propability1" : "14",
	"propability2" : "44",
	"propabilityX" : "42",
	"resurse" : "Forebet",
	"team1" : "Santa Gema",
	"team2" : "Tauro FC"
},
{
	"__v" : NumberInt("0"),
	"_id" : ObjectId("5a6a026a793ed70468152386"),
	"addedDate" : ISODate("2018-01-25T18:14:34.485+02:00"),
	"avarageGoal" : "2.29",
	"correctScore" : "1 - 1",
	"prediction" : "X",
	"propability1" : "34",
	"propability2" : "25",
	"propabilityX" : "41",
	"resurse" : "Forebet",
	"team1" : "Alianza FC (PAN)",
	"team2" : "Sporting San Miguelito"
},
{
	"__v" : NumberInt("0"),
	"_id" : ObjectId("5a6a026a793ed70468152387"),
	"addedDate" : ISODate("2018-01-25T18:14:34.485+02:00"),
	"avarageGoal" : "",
	"correctScore" : "",
	"prediction" : "",
	"propability1" : "X",
	"propability2" : "",
	"propabilityX" : "",
	"resurse" : "Forebet",
	"team1" : "Eintracht Frankfurt",
	"team2" : "M&#xF6;nchengladbach"
},
